[
    {
        "_id": {
            "$oid": "639e32481689ce04c6c77304"
        },
        "user_id": {
            "$uuid": "34d4e435ae5b429f8f5e7f27a3bfa8cf"
        },
        "metadata": {
            "key": "analysis/cleaned_section",
            "platform": "server",
            "write_ts": 1671311944.917506,
            "time_zone": "America/Los_Angeles",
            "write_local_dt": {
                "year": 2022,
                "month": 12,
                "day": 17,
                "hour": 13,
                "minute": 19,
                "second": 4,
                "weekday": 5,
                "timezone": "America/Los_Angeles"
            },
            "write_fmt_time": "2022-12-17T13:19:04.917506-08:00"
        },
        "data": {
            "source": "SmoothedHighConfidenceMotion",
            "trip_id": {
                "$oid": "639e32481689ce04c6c77302"
            },
            "start_ts": 1565570554.2809932,
            "start_local_dt": {
                "year": 2019,
                "month": 8,
                "day": 11,
                "hour": 17,
                "minute": 42,
                "second": 34,
                "weekday": 6,
                "timezone": "America/Los_Angeles"
            },
            "start_fmt_time": "2019-08-11T17:42:34.280993-07:00",
            "start_loc": {
                "type": "Point",
                "coordinates": [
                    -122.08644169,
                    37.39098299
                ]
            },
            "end_ts": 1565570977.09,
            "end_local_dt": {
                "year": 2019,
                "month": 8,
                "day": 11,
                "hour": 17,
                "minute": 49,
                "second": 37,
                "weekday": 6,
                "timezone": "America/Los_Angeles"
            },
            "end_fmt_time": "2019-08-11T17:49:37.090000-07:00",
            "end_loc": {
                "type": "Point",
                "coordinates": [
                    -122.0838293,
                    37.3904425
                ]
            },
            "duration": 422.809006690979,
            "speeds": [
                0.0,
                0.1674801050108117,
                1.000266682645271,
                1.0002671133840884,
                1.0002675441516473,
                1.029003914250955,
                1.0242171770730266,
                1.1079185704606982,
                0.9957084442432846,
                1.1388646478414453,
                0.700723657399499,
                1.392839789450217,
                1.238230740886608,
                1.1824414011788353,
                0.156087035481754,
                0.5156528676737335
            ],
            "distances": [
                0.0,
                5.024403150324351,
                30.00800047935813,
                30.008013401522653,
                30.00802632454942,
                30.87011742752865,
                30.7265153121908,
                33.23755711382095,
                29.87125332729854,
                34.16593943524336,
                21.021709721984973,
                41.785193683506506,
                37.14692222659824,
                35.47324203536506,
                4.682611064452621,
                1.4484723555180283
            ],
            "distance": 395.4779770592623,
            "sensed_mode": 2,
            "write_ts": 1671311944.917506
        }
    },
    {
        "_id": {
            "$oid": "639e32491689ce04c6c77316"
        },
        "user_id": {
            "$uuid": "34d4e435ae5b429f8f5e7f27a3bfa8cf"
        },
        "metadata": {
            "key": "analysis/cleaned_section",
            "platform": "server",
            "write_ts": 1671311945.329857,
            "time_zone": "America/Los_Angeles",
            "write_local_dt": {
                "year": 2022,
                "month": 12,
                "day": 17,
                "hour": 13,
                "minute": 19,
                "second": 5,
                "weekday": 5,
                "timezone": "America/Los_Angeles"
            },
            "write_fmt_time": "2022-12-17T13:19:05.329857-08:00"
        },
        "data": {
            "source": "SmoothedHighConfidenceMotion",
            "trip_id": {
                "$oid": "639e32491689ce04c6c77315"
            },
            "start_ts": 1565571400.0,
            "start_local_dt": {
                "year": 2019,
                "month": 8,
                "day": 11,
                "hour": 17,
                "minute": 56,
                "second": 40,
                "weekday": 6,
                "timezone": "America/Los_Angeles"
            },
            "start_fmt_time": "2019-08-11T17:56:40-07:00",
            "start_loc": {
                "type": "Point",
                "coordinates": [
                    -122.08812123,
                    37.38796978
                ]
            },
            "end_ts": 1565571974.0,
            "end_local_dt": {
                "year": 2019,
                "month": 8,
                "day": 11,
                "hour": 18,
                "minute": 6,
                "second": 14,
                "weekday": 6,
                "timezone": "America/Los_Angeles"
            },
            "end_fmt_time": "2019-08-11T18:06:14-07:00",
            "end_loc": {
                "type": "Point",
                "coordinates": [
                    -122.11271874,
                    37.38079407
                ]
            },
            "duration": 574.0,
            "speeds": [
                0.0,
                4.6651312704161745,
                7.014112423446957,
                7.370056468795217,
                5.902812782640717,
                3.878715475211186,
                7.351271091845805,
                13.420274758771109,
                4.292599827161999,
                12.85088950630535,
                6.882472723793871,
                4.813718354933451,
                6.641234014459233,
                8.524413661772552,
                4.169454695530139,
                6.689232174527783,
                3.256041753058269,
                0.8087016766710532,
                1.2517835898686696,
                0.40572493658115627,
                1.227023878926696
            ],
            "distances": [
                0.0,
                139.95393811248525,
                210.42337270340872,
                221.1016940638565,
                177.0843834792215,
                116.36146425633558,
                220.53813275537416,
                402.60824276313326,
                128.77799481486,
                385.5266851891605,
                206.47418171381614,
                144.41155064800353,
                199.237020433777,
                255.7324098531766,
                125.08364086590419,
                200.67696523583348,
                97.68125259174806,
                24.261050300131597,
                37.55350769606009,
                12.171748097434689,
                4.908095515706784
            ],
            "distance": 3310.567331089428,
            "sensed_mode": 0,
            "end_stop": {
                "$oid": "639e32491689ce04c6c77336"
            },
            "write_ts": 1671311945.329857
        }
    },
    {
        "_id": {
            "$oid": "639e32491689ce04c6c7732c"
        },
        "user_id": {
            "$uuid": "34d4e435ae5b429f8f5e7f27a3bfa8cf"
        },
        "metadata": {
            "key": "analysis/cleaned_section",
            "platform": "server",
            "write_ts": 1671311945.388061,
            "time_zone": "America/Los_Angeles",
            "write_local_dt": {
                "year": 2022,
                "month": 12,
                "day": 17,
                "hour": 13,
                "minute": 19,
                "second": 5,
                "weekday": 5,
                "timezone": "America/Los_Angeles"
            },
            "write_fmt_time": "2022-12-17T13:19:05.388061-08:00"
        },
        "data": {
            "source": "SmoothedHighConfidenceMotion",
            "trip_id": {
                "$oid": "639e32491689ce04c6c77315"
            },
            "start_ts": 1565571975.0,
            "start_local_dt": {
                "year": 2019,
                "month": 8,
                "day": 11,
                "hour": 18,
                "minute": 6,
                "second": 15,
                "weekday": 6,
                "timezone": "America/Los_Angeles"
            },
            "start_fmt_time": "2019-08-11T18:06:15-07:00",
            "start_loc": {
                "type": "Point",
                "coordinates": [
                    -122.11271859,
                    37.38078262
                ]
            },
            "end_ts": 1565572106.962,
            "end_local_dt": {
                "year": 2019,
                "month": 8,
                "day": 11,
                "hour": 18,
                "minute": 8,
                "second": 26,
                "weekday": 6,
                "timezone": "America/Los_Angeles"
            },
            "end_fmt_time": "2019-08-11T18:08:26.962000-07:00",
            "end_loc": {
                "type": "Point",
                "coordinates": [
                    -122.1133119,
                    37.3808825
                ]
            },
            "duration": 131.96199989318848,
            "speeds": [
                0.0,
                2.836812037178551,
                1.0924025195566662,
                1.550439321540172,
                0.3449056522687966,
                0.07885711486820508
            ],
            "distances": [
                0.0,
                85.10436111535653,
                32.772075586699984,
                46.51317964620516,
                10.347169568063897,
                0.9432887996306206
            ],
            "distance": 175.68007471595615,
            "sensed_mode": 2,
            "start_stop": {
                "$oid": "639e32491689ce04c6c77336"
            },
            "end_stop": {
                "$oid": "639e32491689ce04c6c77337"
            },
            "write_ts": 1671311945.388061
        }
    },
    {
        "_id": {
            "$oid": "639e32491689ce04c6c77333"
        },
        "user_id": {
            "$uuid": "34d4e435ae5b429f8f5e7f27a3bfa8cf"
        },
        "metadata": {
            "key": "analysis/cleaned_section",
            "platform": "server",
            "write_ts": 1671311945.4446862,
            "time_zone": "America/Los_Angeles",
            "write_local_dt": {
                "year": 2022,
                "month": 12,
                "day": 17,
                "hour": 13,
                "minute": 19,
                "second": 5,
                "weekday": 5,
                "timezone": "America/Los_Angeles"
            },
            "write_fmt_time": "2022-12-17T13:19:05.444686-08:00"
        },
        "data": {
            "source": "SmoothedHighConfidenceMotion",
            "trip_id": {
                "$oid": "639e32491689ce04c6c77315"
            },
            "start_ts": 1565572197.0,
            "start_local_dt": {
                "year": 2019,
                "month": 8,
                "day": 11,
                "hour": 18,
                "minute": 9,
                "second": 57,
                "weekday": 6,
                "timezone": "America/Los_Angeles"
            },
            "start_fmt_time": "2019-08-11T18:09:57-07:00",
            "start_loc": {
                "type": "Point",
                "coordinates": [
                    -122.11342834,
                    37.38085139
                ]
            },
            "end_ts": 1565572198.0,
            "end_local_dt": {
                "year": 2019,
                "month": 8,
                "day": 11,
                "hour": 18,
                "minute": 9,
                "second": 58,
                "weekday": 6,
                "timezone": "America/Los_Angeles"
            },
            "end_fmt_time": "2019-08-11T18:09:58-07:00",
            "end_loc": {
                "type": "Point",
                "coordinates": [
                    -122.11340657,
                    37.38086502
                ]
            },
            "duration": 1.0,
            "speeds": [
                0.0,
                2.448880309031507
            ],
            "distances": [
                0.0,
                2.448880309031507
            ],
            "distance": 2.448880309031507,
            "sensed_mode": 1,
            "start_stop": {
                "$oid": "639e32491689ce04c6c77337"
            },
            "write_ts": 1671311945.4446862
        }
    },
    {
        "_id": {
            "$oid": "639e324a1689ce04c6c7733a"
        },
        "user_id": {
            "$uuid": "34d4e435ae5b429f8f5e7f27a3bfa8cf"
        },
        "metadata": {
            "key": "analysis/cleaned_section",
            "platform": "server",
            "write_ts": 1671311946.081231,
            "time_zone": "America/Los_Angeles",
            "write_local_dt": {
                "year": 2022,
                "month": 12,
                "day": 17,
                "hour": 13,
                "minute": 19,
                "second": 6,
                "weekday": 5,
                "timezone": "America/Los_Angeles"
            },
            "write_fmt_time": "2022-12-17T13:19:06.081231-08:00"
        },
        "data": {
            "source": "SmoothedHighConfidenceMotion",
            "trip_id": {
                "$oid": "639e32491689ce04c6c77338"
            },
            "start_ts": 1565575943.072151,
            "start_local_dt": {
                "year": 2019,
                "month": 8,
                "day": 11,
                "hour": 19,
                "minute": 12,
                "second": 23,
                "weekday": 6,
                "timezone": "America/Los_Angeles"
            },
            "start_fmt_time": "2019-08-11T19:12:23.072151-07:00",
            "start_loc": {
                "type": "Point",
                "coordinates": [
                    -122.11356346,
                    37.38109809
                ]
            },
            "end_ts": 1565577016.0,
            "end_local_dt": {
                "year": 2019,
                "month": 8,
                "day": 11,
                "hour": 19,
                "minute": 30,
                "second": 16,
                "weekday": 6,
                "timezone": "America/Los_Angeles"
            },
            "end_fmt_time": "2019-08-11T19:30:16-07:00",
            "end_loc": {
                "type": "Point",
                "coordinates": [
                    -122.08357253,
                    37.39075914
                ]
            },
            "duration": 1072.9278490543365,
            "speeds": [
                0.0,
                3.9673907157897994,
                3.170349990436553,
                2.4886554768532627,
                3.6306968654112435,
                4.488834611011708,
                3.3303195287025895,
                4.62104592764222,
                3.9171501586082775,
                4.506340644579301,
                3.711687380055888,
                2.5115509176166357,
                5.32531093227766,
                5.6588497726194165,
                5.6766852366877405,
                2.9266266637489937,
                3.8624785602164047,
                4.5315066957723396,
                4.560496784067548,
                3.2958466537313553,
                4.17382504178333,
                2.9569956003847246,
                2.63992143995101,
                1.8592806004306197,
                2.101138310688687,
                1.5486684994884952,
                0.06310807647682834,
                1.0688841674233034,
                0.12106340948497853,
                0.02472296213115342,
                1.087683028222369,
                3.95257721179554,
                4.562793706566532,
                3.4919673608166257,
                3.832870223811277,
                4.616850846541483,
                1.2164312990592705
            ],
            "distances": [
                0.0,
                119.02172147369399,
                95.11049971309659,
                74.65966430559789,
                108.9209059623373,
                134.66503833035122,
                99.90958586107769,
                138.63137782926663,
                117.51450475824832,
                135.19021933737903,
                111.35062140167665,
                75.34652752849907,
                159.7593279683298,
                169.7654931785825,
                170.3005571006322,
                87.79879991246982,
                115.87435680649214,
                135.9452008731702,
                136.81490352202644,
                98.87539961194067,
                125.2147512534999,
                88.70986801154174,
                79.1976431985303,
                55.77841801291859,
                63.0341493206606,
                46.46005498465485,
                1.8932422943048504,
                32.0665250226991,
                3.631902284549356,
                0.7416888639346025,
                32.63049084667107,
                118.5773163538662,
                136.88381119699594,
                104.75902082449878,
                114.9861067143383,
                138.50552539624448,
                27.890153209801475
            ],
            "distance": 3456.415373264578,
            "sensed_mode": 1,
            "write_ts": 1671311946.081231
        }
    }
]