[
    {
        "_id": {
            "$oid": "5d3794d6b88f219ca094f75a"
        },
        "metadata": {
            "time_zone": "America/Los_Angeles",
            "plugin": "none",
            "write_ts": 1563896695.547351,
            "platform": "ios",
            "read_ts": 0,
            "key": "statemachine/transition",
            "type": "message"
        },
        "user_id": {
            "$uuid": "ccc6a6753e084077b0159ac27cd7eea6"
        },
        "data": {
            "currState": "STATE_TRACKING_STOPPED",
            "transition": "T_START_TRACKING",
            "ts": 1563896695.547093,
            "write_ts": 1563896695.547351
        }
    },
    {
        "_id": {
            "$oid": "5d3794d6b88f219ca094f75e"
        },
        "metadata": {
            "time_zone": "America/Los_Angeles",
            "plugin": "none",
            "write_ts": 1563896695.6231,
            "platform": "ios",
            "read_ts": 0,
            "key": "statemachine/transition",
            "type": "message"
        },
        "user_id": {
            "$uuid": "ccc6a6753e084077b0159ac27cd7eea6"
        },
        "data": {
            "currState": "STATE_START",
            "transition": "T_INITIALIZE",
            "ts": 1563896695.6224551,
            "write_ts": 1563896695.6231
        }
    },
    {
        "_id": {
            "$oid": "5d3794d6b88f219ca094f762"
        },
        "metadata": {
            "time_zone": "America/Los_Angeles",
            "plugin": "none",
            "write_ts": 1563896696.466751,
            "platform": "ios",
            "read_ts": 0,
            "key": "statemachine/transition",
            "type": "message"
        },
        "user_id": {
            "$uuid": "ccc6a6753e084077b0159ac27cd7eea6"
        },
        "data": {
            "currState": "STATE_START",
            "transition": "T_INIT_COMPLETE",
            "ts": 1563896696.466507,
            "write_ts": 1563896696.466751
        }
    },
    {
        "_id": {
            "$oid": "5d3794d6b88f219ca094f766"
        },
        "metadata": {
            "time_zone": "America/Los_Angeles",
            "plugin": "none",
            "write_ts": 1563897071.148354,
            "platform": "ios",
            "read_ts": 0,
            "key": "statemachine/transition",
            "type": "message"
        },
        "user_id": {
            "$uuid": "ccc6a6753e084077b0159ac27cd7eea6"
        },
        "data": {
            "currState": "STATE_WAITING_FOR_TRIP_START",
            "transition": "T_EXITED_GEOFENCE",
            "ts": 1563897071.148175,
            "write_ts": 1563897071.148354
        }
    },
    {
        "_id": {
            "$oid": "5d3794d6b88f219ca094f76a"
        },
        "metadata": {
            "time_zone": "America/Los_Angeles",
            "plugin": "none",
            "write_ts": 1563897071.231194,
            "platform": "ios",
            "read_ts": 0,
            "key": "statemachine/transition",
            "type": "message"
        },
        "user_id": {
            "$uuid": "ccc6a6753e084077b0159ac27cd7eea6"
        },
        "data": {
            "currState": "STATE_WAITING_FOR_TRIP_START",
            "transition": "T_TRIP_STARTED",
            "ts": 1563897071.230778,
            "write_ts": 1563897071.231194
        }
    },
    {
        "_id": {
            "$oid": "5d3794d6b88f219ca094f76e"
        },
        "metadata": {
            "time_zone": "America/Los_Angeles",
            "plugin": "none",
            "write_ts": 1563897071.347564,
            "platform": "ios",
            "read_ts": 0,
            "key": "statemachine/transition",
            "type": "message"
        },
        "user_id": {
            "$uuid": "ccc6a6753e084077b0159ac27cd7eea6"
        },
        "data": {
            "currState": "STATE_ONGOING_TRIP",
            "transition": "T_TRIP_STARTED",
            "ts": 1563897071.3473191,
            "write_ts": 1563897071.347564
        }
    },
    {
        "_id": {
            "$oid": "5d3794d6b88f219ca094f772"
        },
        "metadata": {
            "time_zone": "America/Los_Angeles",
            "plugin": "none",
            "write_ts": 1563897071.4656,
            "platform": "ios",
            "read_ts": 0,
            "key": "statemachine/transition",
            "type": "message"
        },
        "user_id": {
            "$uuid": "ccc6a6753e084077b0159ac27cd7eea6"
        },
        "data": {
            "currState": "STATE_ONGOING_TRIP",
            "transition": "T_TRIP_RESTARTED",
            "ts": 1563897071.465347,
            "write_ts": 1563897071.4656
        }
    },
    {
        "_id": {
            "$oid": "5d3794d6b88f219ca094f8a0"
        },
        "metadata": {
            "time_zone": "America/Los_Angeles",
            "plugin": "none",
            "write_ts": 1563897245.046454,
            "platform": "ios",
            "read_ts": 0,
            "key": "statemachine/transition",
            "type": "message"
        },
        "user_id": {
            "$uuid": "ccc6a6753e084077b0159ac27cd7eea6"
        },
        "data": {
            "currState": "STATE_ONGOING_TRIP",
            "transition": "T_VISIT_ENDED",
            "ts": 1563897245.045992,
            "write_ts": 1563897245.046454
        }
    },
    {
        "_id": {
            "$oid": "5d3794d7b88f219ca0950e18"
        },
        "metadata": {
            "time_zone": "America/Los_Angeles",
            "plugin": "none",
            "write_ts": 1563898804.433677,
            "platform": "ios",
            "read_ts": 0,
            "key": "statemachine/transition",
            "type": "message"
        },
        "user_id": {
            "$uuid": "ccc6a6753e084077b0159ac27cd7eea6"
        },
        "data": {
            "currState": "STATE_ONGOING_TRIP",
            "transition": "T_VISIT_STARTED",
            "ts": 1563898804.433187,
            "write_ts": 1563898804.433677
        }
    },
    {
        "_id": {
            "$oid": "5d3794d7b88f219ca0950e1c"
        },
        "metadata": {
            "time_zone": "America/Los_Angeles",
            "plugin": "none",
            "write_ts": 1563898804.5190868,
            "platform": "ios",
            "read_ts": 0,
            "key": "statemachine/transition",
            "type": "message"
        },
        "user_id": {
            "$uuid": "ccc6a6753e084077b0159ac27cd7eea6"
        },
        "data": {
            "currState": "STATE_ONGOING_TRIP",
            "transition": "T_TRIP_END_DETECTED",
            "ts": 1563898804.518588,
            "write_ts": 1563898804.5190868
        }
    },
    {
        "_id": {
            "$oid": "5d3794d7b88f219ca0950e24"
        },
        "metadata": {
            "time_zone": "America/Los_Angeles",
            "plugin": "none",
            "write_ts": 1563898806.010641,
            "platform": "ios",
            "read_ts": 0,
            "key": "statemachine/transition",
            "type": "message"
        },
        "user_id": {
            "$uuid": "ccc6a6753e084077b0159ac27cd7eea6"
        },
        "data": {
            "currState": "STATE_ONGOING_TRIP",
            "transition": "T_END_TRIP_TRACKING",
            "ts": 1563898806.010145,
            "write_ts": 1563898806.010641
        }
    },
    {
        "_id": {
            "$oid": "5d3794d7b88f219ca0950e28"
        },
        "metadata": {
            "time_zone": "America/Los_Angeles",
            "plugin": "none",
            "write_ts": 1563898806.1343699,
            "platform": "ios",
            "read_ts": 0,
            "key": "statemachine/transition",
            "type": "message"
        },
        "user_id": {
            "$uuid": "ccc6a6753e084077b0159ac27cd7eea6"
        },
        "data": {
            "currState": "STATE_ONGOING_TRIP",
            "transition": "T_TRIP_ENDED",
            "ts": 1563898806.133872,
            "write_ts": 1563898806.1343699
        }
    },
    {
        "_id": {
            "$oid": "5d3794d7b88f219ca0950e30"
        },
        "metadata": {
            "time_zone": "America/Los_Angeles",
            "plugin": "none",
            "write_ts": 1563898808.93768,
            "platform": "ios",
            "read_ts": 0,
            "key": "statemachine/transition",
            "type": "message"
        },
        "user_id": {
            "$uuid": "ccc6a6753e084077b0159ac27cd7eea6"
        },
        "data": {
            "currState": "STATE_WAITING_FOR_TRIP_START",
            "transition": "T_NOP",
            "ts": 1563898808.9371939,
            "write_ts": 1563898808.93768
        }
    },
    {
        "_id": {
            "$oid": "5d3794d7b88f219ca0950e34"
        },
        "metadata": {
            "time_zone": "America/Los_Angeles",
            "plugin": "none",
            "write_ts": 1563898809.235075,
            "platform": "ios",
            "read_ts": 0,
            "key": "statemachine/transition",
            "type": "message"
        },
        "user_id": {
            "$uuid": "ccc6a6753e084077b0159ac27cd7eea6"
        },
        "data": {
            "currState": "STATE_WAITING_FOR_TRIP_START",
            "transition": "T_NOP",
            "ts": 1563898809.234027,
            "write_ts": 1563898809.235075
        }
    },
    {
        "_id": {
            "$oid": "5d3794d7b88f219ca0950e3a"
        },
        "metadata": {
            "time_zone": "America/Los_Angeles",
            "plugin": "none",
            "write_ts": 1563906706.2270079,
            "platform": "ios",
            "read_ts": 0,
            "key": "statemachine/transition",
            "type": "message"
        },
        "user_id": {
            "$uuid": "ccc6a6753e084077b0159ac27cd7eea6"
        },
        "data": {
            "currState": "STATE_WAITING_FOR_TRIP_START",
            "transition": "T_DATA_PUSHED",
            "ts": 1563906706.224783,
            "write_ts": 1563906706.2270079
        }
    },
    {
        "_id": {
            "$oid": "5d3794d7b88f219ca0950e3e"
        },
        "metadata": {
            "time_zone": "America/Los_Angeles",
            "plugin": "none",
            "write_ts": 1563911689.5735102,
            "platform": "ios",
            "read_ts": 0,
            "key": "statemachine/transition",
            "type": "message"
        },
        "user_id": {
            "$uuid": "ccc6a6753e084077b0159ac27cd7eea6"
        },
        "data": {
            "currState": "STATE_WAITING_FOR_TRIP_START",
            "transition": "T_EXITED_GEOFENCE",
            "ts": 1563911689.572552,
            "write_ts": 1563911689.5735102
        }
    },
    {
        "_id": {
            "$oid": "5d3794d7b88f219ca0950e42"
        },
        "metadata": {
            "time_zone": "America/Los_Angeles",
            "plugin": "none",
            "write_ts": 1563911689.670964,
            "platform": "ios",
            "read_ts": 0,
            "key": "statemachine/transition",
            "type": "message"
        },
        "user_id": {
            "$uuid": "ccc6a6753e084077b0159ac27cd7eea6"
        },
        "data": {
            "currState": "STATE_WAITING_FOR_TRIP_START",
            "transition": "T_TRIP_STARTED",
            "ts": 1563911689.6705499,
            "write_ts": 1563911689.670964
        }
    },
    {
        "_id": {
            "$oid": "5d3794d7b88f219ca0950e46"
        },
        "metadata": {
            "time_zone": "America/Los_Angeles",
            "plugin": "none",
            "write_ts": 1563911689.838944,
            "platform": "ios",
            "read_ts": 0,
            "key": "statemachine/transition",
            "type": "message"
        },
        "user_id": {
            "$uuid": "ccc6a6753e084077b0159ac27cd7eea6"
        },
        "data": {
            "currState": "STATE_ONGOING_TRIP",
            "transition": "T_TRIP_STARTED",
            "ts": 1563911689.83843,
            "write_ts": 1563911689.838944
        }
    },
    {
        "_id": {
            "$oid": "5d3794d7b88f219ca0950e4a"
        },
        "metadata": {
            "time_zone": "America/Los_Angeles",
            "plugin": "none",
            "write_ts": 1563911689.995565,
            "platform": "ios",
            "read_ts": 0,
            "key": "statemachine/transition",
            "type": "message"
        },
        "user_id": {
            "$uuid": "ccc6a6753e084077b0159ac27cd7eea6"
        },
        "data": {
            "currState": "STATE_ONGOING_TRIP",
            "transition": "T_TRIP_RESTARTED",
            "ts": 1563911689.9950151,
            "write_ts": 1563911689.995565
        }
    },
    {
        "_id": {
            "$oid": "5d3794d7b88f219ca0950e4e"
        },
        "metadata": {
            "time_zone": "America/Los_Angeles",
            "plugin": "none",
            "write_ts": 1563911690.2121348,
            "platform": "ios",
            "read_ts": 0,
            "key": "statemachine/transition",
            "type": "message"
        },
        "user_id": {
            "$uuid": "ccc6a6753e084077b0159ac27cd7eea6"
        },
        "data": {
            "currState": "STATE_ONGOING_TRIP",
            "transition": "T_VISIT_ENDED",
            "ts": 1563911690.21166,
            "write_ts": 1563911690.2121348
        }
    },
    {
        "_id": {
            "$oid": "5d3794d7b88f219ca0950e52"
        },
        "metadata": {
            "time_zone": "America/Los_Angeles",
            "plugin": "none",
            "write_ts": 1563911690.460093,
            "platform": "ios",
            "read_ts": 0,
            "key": "statemachine/transition",
            "type": "message"
        },
        "user_id": {
            "$uuid": "ccc6a6753e084077b0159ac27cd7eea6"
        },
        "data": {
            "currState": "STATE_ONGOING_TRIP",
            "transition": "T_TRIP_RESTARTED",
            "ts": 1563911690.4596472,
            "write_ts": 1563911690.460093
        }
    },
    {
        "_id": {
            "$oid": "5d3794d7b88f219ca0950e56"
        },
        "metadata": {
            "time_zone": "America/Los_Angeles",
            "plugin": "none",
            "write_ts": 1563911690.667799,
            "platform": "ios",
            "read_ts": 0,
            "key": "statemachine/transition",
            "type": "message"
        },
        "user_id": {
            "$uuid": "ccc6a6753e084077b0159ac27cd7eea6"
        },
        "data": {
            "currState": "STATE_ONGOING_TRIP",
            "transition": "T_VISIT_ENDED",
            "ts": 1563911690.667331,
            "write_ts": 1563911690.667799
        }
    },
    {
        "_id": {
            "$oid": "5d3794dbb88f219ca09539ac"
        },
        "metadata": {
            "time_zone": "America/Los_Angeles",
            "plugin": "none",
            "write_ts": 1563915828.3501248,
            "platform": "ios",
            "read_ts": 0,
            "key": "statemachine/transition",
            "type": "message"
        },
        "user_id": {
            "$uuid": "ccc6a6753e084077b0159ac27cd7eea6"
        },
        "data": {
            "currState": "STATE_ONGOING_TRIP",
            "transition": "T_VISIT_STARTED",
            "ts": 1563915828.3496308,
            "write_ts": 1563915828.3501248
        }
    },
    {
        "_id": {
            "$oid": "5d3794dbb88f219ca09539b0"
        },
        "metadata": {
            "time_zone": "America/Los_Angeles",
            "plugin": "none",
            "write_ts": 1563915828.432922,
            "platform": "ios",
            "read_ts": 0,
            "key": "statemachine/transition",
            "type": "message"
        },
        "user_id": {
            "$uuid": "ccc6a6753e084077b0159ac27cd7eea6"
        },
        "data": {
            "currState": "STATE_ONGOING_TRIP",
            "transition": "T_TRIP_END_DETECTED",
            "ts": 1563915828.432428,
            "write_ts": 1563915828.432922
        }
    },
    {
        "_id": {
            "$oid": "5d3794dbb88f219ca09539b4"
        },
        "metadata": {
            "time_zone": "America/Los_Angeles",
            "plugin": "none",
            "write_ts": 1563915829.870497,
            "platform": "ios",
            "read_ts": 0,
            "key": "statemachine/transition",
            "type": "message"
        },
        "user_id": {
            "$uuid": "ccc6a6753e084077b0159ac27cd7eea6"
        },
        "data": {
            "currState": "STATE_ONGOING_TRIP",
            "transition": "T_END_TRIP_TRACKING",
            "ts": 1563915829.870008,
            "write_ts": 1563915829.870497
        }
    },
    {
        "_id": {
            "$oid": "5d3794dbb88f219ca09539b8"
        },
        "metadata": {
            "time_zone": "America/Los_Angeles",
            "plugin": "none",
            "write_ts": 1563915829.9604921,
            "platform": "ios",
            "read_ts": 0,
            "key": "statemachine/transition",
            "type": "message"
        },
        "user_id": {
            "$uuid": "ccc6a6753e084077b0159ac27cd7eea6"
        },
        "data": {
            "currState": "STATE_ONGOING_TRIP",
            "transition": "T_TRIP_ENDED",
            "ts": 1563915829.960013,
            "write_ts": 1563915829.9604921
        }
    },
    {
        "_id": {
            "$oid": "5d3794dbb88f219ca09539c0"
        },
        "metadata": {
            "time_zone": "America/Los_Angeles",
            "plugin": "none",
            "write_ts": 1563915835.593027,
            "platform": "ios",
            "read_ts": 0,
            "key": "statemachine/transition",
            "type": "message"
        },
        "user_id": {
            "$uuid": "ccc6a6753e084077b0159ac27cd7eea6"
        },
        "data": {
            "currState": "STATE_WAITING_FOR_TRIP_START",
            "transition": "T_NOP",
            "ts": 1563915835.592533,
            "write_ts": 1563915835.593027
        }
    },
    {
        "_id": {
            "$oid": "5d3794dbb88f219ca09539c4"
        },
        "metadata": {
            "time_zone": "America/Los_Angeles",
            "plugin": "none",
            "write_ts": 1563915835.723867,
            "platform": "ios",
            "read_ts": 0,
            "key": "statemachine/transition",
            "type": "message"
        },
        "user_id": {
            "$uuid": "ccc6a6753e084077b0159ac27cd7eea6"
        },
        "data": {
            "currState": "STATE_WAITING_FOR_TRIP_START",
            "transition": "T_NOP",
            "ts": 1563915835.723403,
            "write_ts": 1563915835.723867
        }
    }
]