[
    {
        "_id": {
            "$oid": "5d3d3574b88f219ca0a66e9e"
        },
        "metadata": {
            "key": "background/location",
            "platform": "android",
            "read_ts": 0,
            "time_zone": "America/Los_Angeles",
            "type": "sensor-data",
            "write_ts": 1564291253.618
        },
        "user_id": {
            "$uuid": "6a2dbafdef1e404cb61e506b8935dca4"
        },
        "data": {
            "accuracy": 15.433,
            "altitude": -3.4000000953674316,
            "bearing": 0,
            "elapsedRealtimeNanos": 2084197267000000,
            "filter": "time",
            "fmt_time": "Jul 27, 2019 10:20:53 PM",
            "latitude": 37.3910398,
            "longitude": -122.0864652,
            "sensed_speed": 0,
            "ts": 1564291253.545,
            "write_ts": 1564291253.618
        }
    },
    {
        "_id": {
            "$oid": "5d3d3574b88f219ca0a66ea2"
        },
        "metadata": {
            "key": "background/location",
            "platform": "android",
            "read_ts": 0,
            "time_zone": "America/Los_Angeles",
            "type": "sensor-data",
            "write_ts": 1564291279.691
        },
        "user_id": {
            "$uuid": "6a2dbafdef1e404cb61e506b8935dca4"
        },
        "data": {
            "accuracy": 15.433,
            "altitude": -3.4000000953674316,
            "bearing": 0,
            "elapsedRealtimeNanos": 2084223350000000,
            "filter": "time",
            "fmt_time": "Jul 27, 2019 10:21:19 PM",
            "latitude": 37.3910398,
            "longitude": -122.0864652,
            "sensed_speed": 0,
            "ts": 1564291279.627,
            "write_ts": 1564291279.691
        }
    },
    {
        "_id": {
            "$oid": "5d3d3574b88f219ca0a66ea4"
        },
        "metadata": {
            "key": "background/location",
            "platform": "android",
            "read_ts": 0,
            "time_zone": "America/Los_Angeles",
            "type": "sensor-data",
            "write_ts": 1564291472.207
        },
        "user_id": {
            "$uuid": "6a2dbafdef1e404cb61e506b8935dca4"
        },
        "data": {
            "accuracy": 15.433,
            "altitude": -3.4000000953674316,
            "bearing": 0,
            "elapsedRealtimeNanos": 2084415858000000,
            "filter": "time",
            "fmt_time": "Jul 27, 2019 10:24:32 PM",
            "latitude": 37.3910398,
            "longitude": -122.0864652,
            "sensed_speed": 0,
            "ts": 1564291472.135,
            "write_ts": 1564291472.207
        }
    },
    {
        "_id": {
            "$oid": "5d3d3574b88f219ca0a66ea6"
        },
        "metadata": {
            "key": "background/location",
            "platform": "android",
            "read_ts": 0,
            "time_zone": "America/Los_Angeles",
            "type": "sensor-data",
            "write_ts": 1564291511.709
        },
        "user_id": {
            "$uuid": "6a2dbafdef1e404cb61e506b8935dca4"
        },
        "data": {
            "accuracy": 15.433,
            "altitude": -3.4000000953674316,
            "bearing": 0,
            "elapsedRealtimeNanos": 2084455362000000,
            "filter": "time",
            "fmt_time": "Jul 27, 2019 10:25:11 PM",
            "latitude": 37.3910398,
            "longitude": -122.0864652,
            "sensed_speed": 0,
            "ts": 1564291511.64,
            "write_ts": 1564291511.709
        }
    },
    {
        "_id": {
            "$oid": "5d3d3574b88f219ca0a66ea8"
        },
        "metadata": {
            "key": "background/location",
            "platform": "android",
            "read_ts": 0,
            "time_zone": "America/Los_Angeles",
            "type": "sensor-data",
            "write_ts": 1564291554.719
        },
        "user_id": {
            "$uuid": "6a2dbafdef1e404cb61e506b8935dca4"
        },
        "data": {
            "accuracy": 15.433,
            "altitude": -3.4000000953674316,
            "bearing": 0,
            "elapsedRealtimeNanos": 2084498358000000,
            "filter": "time",
            "fmt_time": "Jul 27, 2019 10:25:54 PM",
            "latitude": 37.3910398,
            "longitude": -122.0864652,
            "sensed_speed": 0,
            "ts": 1564291554.635,
            "write_ts": 1564291554.719
        }
    },
    {
        "_id": {
            "$oid": "5d3d3574b88f219ca0a66eaa"
        },
        "metadata": {
            "key": "background/location",
            "platform": "android",
            "read_ts": 0,
            "time_zone": "America/Los_Angeles",
            "type": "sensor-data",
            "write_ts": 1564291742.83
        },
        "user_id": {
            "$uuid": "6a2dbafdef1e404cb61e506b8935dca4"
        },
        "data": {
            "accuracy": 1000,
            "altitude": 0,
            "bearing": 0,
            "elapsedRealtimeNanos": 2084686454000000,
            "filter": "time",
            "fmt_time": "Jul 27, 2019 10:29:02 PM",
            "latitude": 37.3925796,
            "longitude": -122.0942186,
            "sensed_speed": 0,
            "ts": 1564291742.732,
            "write_ts": 1564291742.83
        }
    },
    {
        "_id": {
            "$oid": "5d3d3574b88f219ca0a66eac"
        },
        "metadata": {
            "key": "background/location",
            "platform": "android",
            "read_ts": 0,
            "time_zone": "America/Los_Angeles",
            "type": "sensor-data",
            "write_ts": 1564291855.815
        },
        "user_id": {
            "$uuid": "6a2dbafdef1e404cb61e506b8935dca4"
        },
        "data": {
            "accuracy": 1000,
            "altitude": 0,
            "bearing": 0,
            "elapsedRealtimeNanos": 2084799468000000,
            "filter": "time",
            "fmt_time": "Jul 27, 2019 10:30:55 PM",
            "latitude": 37.3925796,
            "longitude": -122.0942186,
            "sensed_speed": 0,
            "ts": 1564291855.745,
            "write_ts": 1564291855.815
        }
    },
    {
        "_id": {
            "$oid": "5d3d3574b88f219ca0a66eae"
        },
        "metadata": {
            "key": "background/location",
            "platform": "android",
            "read_ts": 0,
            "time_zone": "America/Los_Angeles",
            "type": "sensor-data",
            "write_ts": 1564291974.643
        },
        "user_id": {
            "$uuid": "6a2dbafdef1e404cb61e506b8935dca4"
        },
        "data": {
            "accuracy": 1000,
            "altitude": 0,
            "bearing": 0,
            "elapsedRealtimeNanos": 2084918257000000,
            "filter": "time",
            "fmt_time": "Jul 27, 2019 10:32:54 PM",
            "latitude": 37.3925796,
            "longitude": -122.0942186,
            "sensed_speed": 0,
            "ts": 1564291974.535,
            "write_ts": 1564291974.643
        }
    },
    {
        "_id": {
            "$oid": "5d3d3574b88f219ca0a66eb0"
        },
        "metadata": {
            "key": "background/location",
            "platform": "android",
            "read_ts": 0,
            "time_zone": "America/Los_Angeles",
            "type": "sensor-data",
            "write_ts": 1564292157.769
        },
        "user_id": {
            "$uuid": "6a2dbafdef1e404cb61e506b8935dca4"
        },
        "data": {
            "accuracy": 1000,
            "altitude": 0,
            "bearing": 0,
            "elapsedRealtimeNanos": 2085101410000000,
            "filter": "time",
            "fmt_time": "Jul 27, 2019 10:35:57 PM",
            "latitude": 37.3925796,
            "longitude": -122.0942186,
            "sensed_speed": 0,
            "ts": 1564292157.688,
            "write_ts": 1564292157.769
        }
    },
    {
        "_id": {
            "$oid": "5d3d3574b88f219ca0a66eb2"
        },
        "metadata": {
            "key": "background/location",
            "platform": "android",
            "read_ts": 0,
            "time_zone": "America/Los_Angeles",
            "type": "sensor-data",
            "write_ts": 1564292206.747
        },
        "user_id": {
            "$uuid": "6a2dbafdef1e404cb61e506b8935dca4"
        },
        "data": {
            "accuracy": 1000,
            "altitude": 0,
            "bearing": 0,
            "elapsedRealtimeNanos": 2085150404000000,
            "filter": "time",
            "fmt_time": "Jul 27, 2019 10:36:46 PM",
            "latitude": 37.3925796,
            "longitude": -122.0942186,
            "sensed_speed": 0,
            "ts": 1564292206.682,
            "write_ts": 1564292206.747
        }
    },
    {
        "_id": {
            "$oid": "5d3d3574b88f219ca0a66eb4"
        },
        "metadata": {
            "key": "background/location",
            "platform": "android",
            "read_ts": 0,
            "time_zone": "America/Los_Angeles",
            "type": "sensor-data",
            "write_ts": 1564292437.773
        },
        "user_id": {
            "$uuid": "6a2dbafdef1e404cb61e506b8935dca4"
        },
        "data": {
            "accuracy": 1000,
            "altitude": 0,
            "bearing": 0,
            "elapsedRealtimeNanos": 2085381404000000,
            "filter": "time",
            "fmt_time": "Jul 27, 2019 10:40:37 PM",
            "latitude": 37.3925796,
            "longitude": -122.0942186,
            "sensed_speed": 0,
            "ts": 1564292437.681,
            "write_ts": 1564292437.773
        }
    },
    {
        "_id": {
            "$oid": "5d3d3574b88f219ca0a66eb6"
        },
        "metadata": {
            "key": "background/location",
            "platform": "android",
            "read_ts": 0,
            "time_zone": "America/Los_Angeles",
            "type": "sensor-data",
            "write_ts": 1564292458.775
        },
        "user_id": {
            "$uuid": "6a2dbafdef1e404cb61e506b8935dca4"
        },
        "data": {
            "accuracy": 1000,
            "altitude": 0,
            "bearing": 0,
            "elapsedRealtimeNanos": 2085402409000000,
            "filter": "time",
            "fmt_time": "Jul 27, 2019 10:40:58 PM",
            "latitude": 37.3925796,
            "longitude": -122.0942186,
            "sensed_speed": 0,
            "ts": 1564292458.687,
            "write_ts": 1564292458.775
        }
    },
    {
        "_id": {
            "$oid": "5d3d3574b88f219ca0a66eb8"
        },
        "metadata": {
            "key": "background/location",
            "platform": "android",
            "read_ts": 0,
            "time_zone": "America/Los_Angeles",
            "type": "sensor-data",
            "write_ts": 1564292467.762
        },
        "user_id": {
            "$uuid": "6a2dbafdef1e404cb61e506b8935dca4"
        },
        "data": {
            "accuracy": 1000,
            "altitude": 0,
            "bearing": 0,
            "elapsedRealtimeNanos": 2085411419000000,
            "filter": "time",
            "fmt_time": "Jul 27, 2019 10:41:07 PM",
            "latitude": 37.3925796,
            "longitude": -122.0942186,
            "sensed_speed": 0,
            "ts": 1564292467.697,
            "write_ts": 1564292467.762
        }
    },
    {
        "_id": {
            "$oid": "5d3d4da2b88f219ca0a690bf"
        },
        "metadata": {
            "key": "background/location",
            "platform": "android",
            "read_ts": 0,
            "time_zone": "America/Los_Angeles",
            "type": "sensor-data",
            "write_ts": 1564292668.753
        },
        "user_id": {
            "$uuid": "6a2dbafdef1e404cb61e506b8935dca4"
        },
        "data": {
            "accuracy": 1000,
            "altitude": 0,
            "bearing": 0,
            "elapsedRealtimeNanos": 2085612391000000,
            "filter": "time",
            "fmt_time": "Jul 27, 2019 10:44:28 PM",
            "latitude": 37.3925796,
            "longitude": -122.0942186,
            "sensed_speed": 0,
            "ts": 1564292668.669,
            "write_ts": 1564292668.753
        }
    },
    {
        "_id": {
            "$oid": "5d3d4da2b88f219ca0a690c1"
        },
        "metadata": {
            "key": "background/location",
            "platform": "android",
            "read_ts": 0,
            "time_zone": "America/Los_Angeles",
            "type": "sensor-data",
            "write_ts": 1564292759.762
        },
        "user_id": {
            "$uuid": "6a2dbafdef1e404cb61e506b8935dca4"
        },
        "data": {
            "accuracy": 1000,
            "altitude": 0,
            "bearing": 0,
            "elapsedRealtimeNanos": 2085703413000000,
            "filter": "time",
            "fmt_time": "Jul 27, 2019 10:45:59 PM",
            "latitude": 37.3925796,
            "longitude": -122.0942186,
            "sensed_speed": 0,
            "ts": 1564292759.69,
            "write_ts": 1564292759.762
        }
    },
    {
        "_id": {
            "$oid": "5d3d4da2b88f219ca0a690c3"
        },
        "metadata": {
            "key": "background/location",
            "platform": "android",
            "read_ts": 0,
            "time_zone": "America/Los_Angeles",
            "type": "sensor-data",
            "write_ts": 1564292990.833
        },
        "user_id": {
            "$uuid": "6a2dbafdef1e404cb61e506b8935dca4"
        },
        "data": {
            "accuracy": 1000,
            "altitude": 0,
            "bearing": 0,
            "elapsedRealtimeNanos": 2085934451000000,
            "filter": "time",
            "fmt_time": "Jul 27, 2019 10:49:50 PM",
            "latitude": 37.3925796,
            "longitude": -122.0942186,
            "sensed_speed": 0,
            "ts": 1564292990.729,
            "write_ts": 1564292990.833
        }
    },
    {
        "_id": {
            "$oid": "5d3d4da2b88f219ca0a690c5"
        },
        "metadata": {
            "key": "background/location",
            "platform": "android",
            "read_ts": 0,
            "time_zone": "America/Los_Angeles",
            "type": "sensor-data",
            "write_ts": 1564293060.793
        },
        "user_id": {
            "$uuid": "6a2dbafdef1e404cb61e506b8935dca4"
        },
        "data": {
            "accuracy": 1000,
            "altitude": 0,
            "bearing": 0,
            "elapsedRealtimeNanos": 2086004444000000,
            "filter": "time",
            "fmt_time": "Jul 27, 2019 10:51:00 PM",
            "latitude": 37.3925796,
            "longitude": -122.0942186,
            "sensed_speed": 0,
            "ts": 1564293060.722,
            "write_ts": 1564293060.793
        }
    },
    {
        "_id": {
            "$oid": "5d3d4da2b88f219ca0a690c7"
        },
        "metadata": {
            "key": "background/location",
            "platform": "android",
            "read_ts": 0,
            "time_zone": "America/Los_Angeles",
            "type": "sensor-data",
            "write_ts": 1564293361.867
        },
        "user_id": {
            "$uuid": "6a2dbafdef1e404cb61e506b8935dca4"
        },
        "data": {
            "accuracy": 800,
            "altitude": 0,
            "bearing": 0,
            "elapsedRealtimeNanos": 2086305514000000,
            "filter": "time",
            "fmt_time": "Jul 27, 2019 10:56:01 PM",
            "latitude": 37.3924793,
            "longitude": -122.0846321,
            "sensed_speed": 0,
            "ts": 1564293361.791,
            "write_ts": 1564293361.867
        }
    },
    {
        "_id": {
            "$oid": "5d3d4da2b88f219ca0a690c9"
        },
        "metadata": {
            "key": "background/location",
            "platform": "android",
            "read_ts": 0,
            "time_zone": "America/Los_Angeles",
            "type": "sensor-data",
            "write_ts": 1564293480.758
        },
        "user_id": {
            "$uuid": "6a2dbafdef1e404cb61e506b8935dca4"
        },
        "data": {
            "accuracy": 1000,
            "altitude": 0,
            "bearing": 0,
            "elapsedRealtimeNanos": 2086424393000000,
            "filter": "time",
            "fmt_time": "Jul 27, 2019 10:58:00 PM",
            "latitude": 37.3925796,
            "longitude": -122.0942186,
            "sensed_speed": 0,
            "ts": 1564293480.67,
            "write_ts": 1564293480.758
        }
    },
    {
        "_id": {
            "$oid": "5d3d4da2b88f219ca0a690cb"
        },
        "metadata": {
            "key": "background/location",
            "platform": "android",
            "read_ts": 0,
            "time_zone": "America/Los_Angeles",
            "type": "sensor-data",
            "write_ts": 1564293665.865
        },
        "user_id": {
            "$uuid": "6a2dbafdef1e404cb61e506b8935dca4"
        },
        "data": {
            "accuracy": 1000,
            "altitude": 0,
            "bearing": 0,
            "elapsedRealtimeNanos": 2086609456000000,
            "filter": "time",
            "fmt_time": "Jul 27, 2019 11:01:05 PM",
            "latitude": 37.3925796,
            "longitude": -122.0942186,
            "sensed_speed": 0,
            "ts": 1564293665.733,
            "write_ts": 1564293665.865
        }
    },
    {
        "_id": {
            "$oid": "5d3d4da2b88f219ca0a690cd"
        },
        "metadata": {
            "key": "background/location",
            "platform": "android",
            "read_ts": 0,
            "time_zone": "America/Los_Angeles",
            "type": "sensor-data",
            "write_ts": 1564293966.869
        },
        "user_id": {
            "$uuid": "6a2dbafdef1e404cb61e506b8935dca4"
        },
        "data": {
            "accuracy": 1000,
            "altitude": 0,
            "bearing": 0,
            "elapsedRealtimeNanos": 2086910496000000,
            "filter": "time",
            "fmt_time": "Jul 27, 2019 11:06:06 PM",
            "latitude": 37.3925796,
            "longitude": -122.0942186,
            "sensed_speed": 0,
            "ts": 1564293966.774,
            "write_ts": 1564293966.869
        }
    },
    {
        "_id": {
            "$oid": "5d3d4da2b88f219ca0a690cf"
        },
        "metadata": {
            "key": "background/location",
            "platform": "android",
            "read_ts": 0,
            "time_zone": "America/Los_Angeles",
            "type": "sensor-data",
            "write_ts": 1564294032.803
        },
        "user_id": {
            "$uuid": "6a2dbafdef1e404cb61e506b8935dca4"
        },
        "data": {
            "accuracy": 1000,
            "altitude": 0,
            "bearing": 0,
            "elapsedRealtimeNanos": 2086976450000000,
            "filter": "time",
            "fmt_time": "Jul 27, 2019 11:07:12 PM",
            "latitude": 37.3925796,
            "longitude": -122.0942186,
            "sensed_speed": 0,
            "ts": 1564294032.728,
            "write_ts": 1564294032.803
        }
    },
    {
        "_id": {
            "$oid": "5d3d4da2b88f219ca0a690d1"
        },
        "metadata": {
            "key": "background/location",
            "platform": "android",
            "read_ts": 0,
            "time_zone": "America/Los_Angeles",
            "type": "sensor-data",
            "write_ts": 1564294267.787
        },
        "user_id": {
            "$uuid": "6a2dbafdef1e404cb61e506b8935dca4"
        },
        "data": {
            "accuracy": 1000,
            "altitude": 0,
            "bearing": 0,
            "elapsedRealtimeNanos": 2087211450000000,
            "filter": "time",
            "fmt_time": "Jul 27, 2019 11:11:07 PM",
            "latitude": 37.3925796,
            "longitude": -122.0942186,
            "sensed_speed": 0,
            "ts": 1564294267.727,
            "write_ts": 1564294267.787
        }
    },
    {
        "_id": {
            "$oid": "5d3d4da2b88f219ca0a690d3"
        },
        "metadata": {
            "key": "background/location",
            "platform": "android",
            "read_ts": 0,
            "time_zone": "America/Los_Angeles",
            "type": "sensor-data",
            "write_ts": 1564294568.802
        },
        "user_id": {
            "$uuid": "6a2dbafdef1e404cb61e506b8935dca4"
        },
        "data": {
            "accuracy": 1000,
            "altitude": 0,
            "bearing": 0,
            "elapsedRealtimeNanos": 2087512448000000,
            "filter": "time",
            "fmt_time": "Jul 27, 2019 11:16:08 PM",
            "latitude": 37.3925796,
            "longitude": -122.0942186,
            "sensed_speed": 0,
            "ts": 1564294568.726,
            "write_ts": 1564294568.802
        }
    },
    {
        "_id": {
            "$oid": "5d3d4da2b88f219ca0a690d5"
        },
        "metadata": {
            "key": "background/location",
            "platform": "android",
            "read_ts": 0,
            "time_zone": "America/Los_Angeles",
            "type": "sensor-data",
            "write_ts": 1564294584.799
        },
        "user_id": {
            "$uuid": "6a2dbafdef1e404cb61e506b8935dca4"
        },
        "data": {
            "accuracy": 1000,
            "altitude": 0,
            "bearing": 0,
            "elapsedRealtimeNanos": 2087528437000000,
            "filter": "time",
            "fmt_time": "Jul 27, 2019 11:16:24 PM",
            "latitude": 37.3925796,
            "longitude": -122.0942186,
            "sensed_speed": 0,
            "ts": 1564294584.714,
            "write_ts": 1564294584.799
        }
    },
    {
        "_id": {
            "$oid": "5d3d4da2b88f219ca0a690d7"
        },
        "metadata": {
            "key": "background/location",
            "platform": "android",
            "read_ts": 0,
            "time_zone": "America/Los_Angeles",
            "type": "sensor-data",
            "write_ts": 1564294870.766
        },
        "user_id": {
            "$uuid": "6a2dbafdef1e404cb61e506b8935dca4"
        },
        "data": {
            "accuracy": 1000,
            "altitude": 0,
            "bearing": 0,
            "elapsedRealtimeNanos": 2087814406000000,
            "filter": "time",
            "fmt_time": "Jul 27, 2019 11:21:10 PM",
            "latitude": 37.3925796,
            "longitude": -122.0942186,
            "sensed_speed": 0,
            "ts": 1564294870.683,
            "write_ts": 1564294870.766
        }
    },
    {
        "_id": {
            "$oid": "5d3d4da2b88f219ca0a690d9"
        },
        "metadata": {
            "key": "background/location",
            "platform": "android",
            "read_ts": 0,
            "time_zone": "America/Los_Angeles",
            "type": "sensor-data",
            "write_ts": 1564295135.861
        },
        "user_id": {
            "$uuid": "6a2dbafdef1e404cb61e506b8935dca4"
        },
        "data": {
            "accuracy": 1000,
            "altitude": 0,
            "bearing": 0,
            "elapsedRealtimeNanos": 2088079494000000,
            "filter": "time",
            "fmt_time": "Jul 27, 2019 11:25:35 PM",
            "latitude": 37.3925796,
            "longitude": -122.0942186,
            "sensed_speed": 0,
            "ts": 1564295135.772,
            "write_ts": 1564295135.861
        }
    },
    {
        "_id": {
            "$oid": "5d3d4da2b88f219ca0a690db"
        },
        "metadata": {
            "key": "background/location",
            "platform": "android",
            "read_ts": 0,
            "time_zone": "America/Los_Angeles",
            "type": "sensor-data",
            "write_ts": 1564295138.507
        },
        "user_id": {
            "$uuid": "6a2dbafdef1e404cb61e506b8935dca4"
        },
        "data": {
            "accuracy": 1000,
            "altitude": 0,
            "bearing": 0,
            "elapsedRealtimeNanos": 2088082170000000,
            "filter": "time",
            "fmt_time": "Jul 27, 2019 11:25:38 PM",
            "latitude": 37.3925796,
            "longitude": -122.0942186,
            "sensed_speed": 0,
            "ts": 1564295138.448,
            "write_ts": 1564295138.507
        }
    },
    {
        "_id": {
            "$oid": "5d3d4da2b88f219ca0a690dd"
        },
        "metadata": {
            "key": "background/location",
            "platform": "android",
            "read_ts": 0,
            "time_zone": "America/Los_Angeles",
            "type": "sensor-data",
            "write_ts": 1564295142.083
        },
        "user_id": {
            "$uuid": "6a2dbafdef1e404cb61e506b8935dca4"
        },
        "data": {
            "accuracy": 3,
            "altitude": 3,
            "bearing": 0,
            "elapsedRealtimeNanos": 2088085701330617,
            "filter": "time",
            "fmt_time": "Jul 27, 2019 11:25:42 PM",
            "latitude": 37.3909835,
            "longitude": -122.0865277,
            "sensed_speed": 0,
            "ts": 1564295142,
            "write_ts": 1564295142.083
        }
    },
    {
        "_id": {
            "$oid": "5d3d4da2b88f219ca0a690df"
        },
        "metadata": {
            "key": "background/location",
            "platform": "android",
            "read_ts": 0,
            "time_zone": "America/Los_Angeles",
            "type": "sensor-data",
            "write_ts": 1564298656.891
        },
        "user_id": {
            "$uuid": "6a2dbafdef1e404cb61e506b8935dca4"
        },
        "data": {
            "accuracy": 3,
            "altitude": 3,
            "bearing": 0,
            "elapsedRealtimeNanos": 2091600511000000,
            "filter": "time",
            "fmt_time": "Jul 28, 2019 12:24:16 AM",
            "latitude": 37.3909835,
            "longitude": -122.0865277,
            "sensed_speed": 0,
            "ts": 1564298656.789,
            "write_ts": 1564298656.891
        }
    },
    {
        "_id": {
            "$oid": "5d3d687bb88f219ca0a69e96"
        },
        "metadata": {
            "key": "background/location",
            "platform": "android",
            "read_ts": 0,
            "time_zone": "America/Los_Angeles",
            "type": "sensor-data",
            "write_ts": 1564298959.565
        },
        "user_id": {
            "$uuid": "6a2dbafdef1e404cb61e506b8935dca4"
        },
        "data": {
            "accuracy": 3,
            "altitude": 3,
            "bearing": 0,
            "elapsedRealtimeNanos": 2091903160000000,
            "filter": "time",
            "fmt_time": "Jul 28, 2019 12:29:19 AM",
            "latitude": 37.3909835,
            "longitude": -122.0865277,
            "sensed_speed": 0,
            "ts": 1564298959.438,
            "write_ts": 1564298959.565
        }
    },
    {
        "_id": {
            "$oid": "5d3d687bb88f219ca0a69e98"
        },
        "metadata": {
            "key": "background/location",
            "platform": "android",
            "read_ts": 0,
            "time_zone": "America/Los_Angeles",
            "type": "sensor-data",
            "write_ts": 1564305529.839
        },
        "user_id": {
            "$uuid": "6a2dbafdef1e404cb61e506b8935dca4"
        },
        "data": {
            "accuracy": 3,
            "altitude": 3,
            "bearing": 0,
            "elapsedRealtimeNanos": 2098473480000000,
            "filter": "time",
            "fmt_time": "Jul 28, 2019 2:18:49 AM",
            "latitude": 37.3909835,
            "longitude": -122.0865277,
            "sensed_speed": 0,
            "ts": 1564305529.758,
            "write_ts": 1564305529.839
        }
    },
    {
        "_id": {
            "$oid": "5d3da1c3b88f219ca0a6bbc6"
        },
        "metadata": {
            "key": "background/location",
            "platform": "android",
            "read_ts": 0,
            "time_zone": "America/Los_Angeles",
            "type": "sensor-data",
            "write_ts": 1564305546.771
        },
        "user_id": {
            "$uuid": "6a2dbafdef1e404cb61e506b8935dca4"
        },
        "data": {
            "accuracy": 3,
            "altitude": 3,
            "bearing": 0,
            "elapsedRealtimeNanos": 2098490452000000,
            "filter": "time",
            "fmt_time": "Jul 28, 2019 2:19:06 AM",
            "latitude": 37.3909835,
            "longitude": -122.0865277,
            "sensed_speed": 0,
            "ts": 1564305546.729,
            "write_ts": 1564305546.771
        }
    },
    {
        "_id": {
            "$oid": "5d3da1c3b88f219ca0a6bbc8"
        },
        "metadata": {
            "key": "background/location",
            "platform": "android",
            "read_ts": 0,
            "time_zone": "America/Los_Angeles",
            "type": "sensor-data",
            "write_ts": 1564305639.838
        },
        "user_id": {
            "$uuid": "6a2dbafdef1e404cb61e506b8935dca4"
        },
        "data": {
            "accuracy": 3,
            "altitude": 3,
            "bearing": 0,
            "elapsedRealtimeNanos": 2098583469000000,
            "filter": "time",
            "fmt_time": "Jul 28, 2019 2:20:39 AM",
            "latitude": 37.3909835,
            "longitude": -122.0865277,
            "sensed_speed": 0,
            "ts": 1564305639.747,
            "write_ts": 1564305639.838
        }
    },
    {
        "_id": {
            "$oid": "5d3da1c3b88f219ca0a6bbca"
        },
        "metadata": {
            "key": "background/location",
            "platform": "android",
            "read_ts": 0,
            "time_zone": "America/Los_Angeles",
            "type": "sensor-data",
            "write_ts": 1564305858.921
        },
        "user_id": {
            "$uuid": "6a2dbafdef1e404cb61e506b8935dca4"
        },
        "data": {
            "accuracy": 3,
            "altitude": 3,
            "bearing": 0,
            "elapsedRealtimeNanos": 2098802548000000,
            "filter": "time",
            "fmt_time": "Jul 28, 2019 2:24:18 AM",
            "latitude": 37.3909835,
            "longitude": -122.0865277,
            "sensed_speed": 0,
            "ts": 1564305858.825,
            "write_ts": 1564305858.921
        }
    },
    {
        "_id": {
            "$oid": "5d3da1c3b88f219ca0a6bbcc"
        },
        "metadata": {
            "key": "background/location",
            "platform": "android",
            "read_ts": 0,
            "time_zone": "America/Los_Angeles",
            "type": "sensor-data",
            "write_ts": 1564306159.884
        },
        "user_id": {
            "$uuid": "6a2dbafdef1e404cb61e506b8935dca4"
        },
        "data": {
            "accuracy": 15.451,
            "altitude": -3.4000000953674316,
            "bearing": 0,
            "elapsedRealtimeNanos": 2099103535000000,
            "filter": "time",
            "fmt_time": "Jul 28, 2019 2:29:19 AM",
            "latitude": 37.3910398,
            "longitude": -122.0864656,
            "sensed_speed": 0,
            "ts": 1564306159.813,
            "write_ts": 1564306159.884
        }
    },
    {
        "_id": {
            "$oid": "5d3da1c3b88f219ca0a6bbce"
        },
        "metadata": {
            "key": "background/location",
            "platform": "android",
            "read_ts": 0,
            "time_zone": "America/Los_Angeles",
            "type": "sensor-data",
            "write_ts": 1564320194.007
        },
        "user_id": {
            "$uuid": "6a2dbafdef1e404cb61e506b8935dca4"
        },
        "data": {
            "accuracy": 1000,
            "altitude": 0,
            "bearing": 0,
            "elapsedRealtimeNanos": 2113137667000000,
            "filter": "time",
            "fmt_time": "Jul 28, 2019 6:23:13 AM",
            "latitude": 37.3925796,
            "longitude": -122.0942186,
            "sensed_speed": 0,
            "ts": 1564320193.944,
            "write_ts": 1564320194.007
        }
    },
    {
        "_id": {
            "$oid": "5d3daaceb88f219ca0a6c1bf"
        },
        "metadata": {
            "key": "background/location",
            "platform": "android",
            "read_ts": 0,
            "time_zone": "America/Los_Angeles",
            "type": "sensor-data",
            "write_ts": 1564320196.917
        },
        "user_id": {
            "$uuid": "6a2dbafdef1e404cb61e506b8935dca4"
        },
        "data": {
            "accuracy": 7,
            "altitude": -3,
            "bearing": 9,
            "elapsedRealtimeNanos": 2113140546279981,
            "filter": "time",
            "fmt_time": "Jul 28, 2019 6:23:16 AM",
            "latitude": 37.3910673,
            "longitude": -122.0865188,
            "sensed_speed": 0.8149233,
            "ts": 1564320196.407,
            "write_ts": 1564320196.917
        }
    },
    {
        "_id": {
            "$oid": "5d3daaceb88f219ca0a6c1c3"
        },
        "metadata": {
            "key": "background/location",
            "platform": "android",
            "read_ts": 0,
            "time_zone": "America/Los_Angeles",
            "type": "sensor-data",
            "write_ts": 1564320197.99
        },
        "user_id": {
            "$uuid": "6a2dbafdef1e404cb61e506b8935dca4"
        },
        "data": {
            "accuracy": 5.899,
            "altitude": -1,
            "bearing": 0,
            "elapsedRealtimeNanos": 2113141644469720,
            "filter": "time",
            "fmt_time": "Jul 28, 2019 6:23:18 AM",
            "latitude": 37.3910636,
            "longitude": -122.0865152,
            "sensed_speed": 0,
            "ts": 1564320198,
            "write_ts": 1564320197.99
        }
    },
    {
        "_id": {
            "$oid": "5d3daaceb88f219ca0a6c1c5"
        },
        "metadata": {
            "key": "background/location",
            "platform": "android",
            "read_ts": 0,
            "time_zone": "America/Los_Angeles",
            "type": "sensor-data",
            "write_ts": 1564320199.011
        },
        "user_id": {
            "$uuid": "6a2dbafdef1e404cb61e506b8935dca4"
        },
        "data": {
            "accuracy": 5.792,
            "altitude": -6,
            "bearing": 0,
            "elapsedRealtimeNanos": 2113142667818313,
            "filter": "time",
            "fmt_time": "Jul 28, 2019 6:23:19 AM",
            "latitude": 37.3910611,
            "longitude": -122.0865158,
            "sensed_speed": 0,
            "ts": 1564320199,
            "write_ts": 1564320199.011
        }
    },
    {
        "_id": {
            "$oid": "5d3daaceb88f219ca0a6c1c7"
        },
        "metadata": {
            "key": "background/location",
            "platform": "android",
            "read_ts": 0,
            "time_zone": "America/Los_Angeles",
            "type": "sensor-data",
            "write_ts": 1564320199.99
        },
        "user_id": {
            "$uuid": "6a2dbafdef1e404cb61e506b8935dca4"
        },
        "data": {
            "accuracy": 5.718,
            "altitude": -6,
            "bearing": 0,
            "elapsedRealtimeNanos": 2113143645296959,
            "filter": "time",
            "fmt_time": "Jul 28, 2019 6:23:20 AM",
            "latitude": 37.3910583,
            "longitude": -122.0865155,
            "sensed_speed": 0,
            "ts": 1564320200,
            "write_ts": 1564320199.99
        }
    },
    {
        "_id": {
            "$oid": "5d3daaceb88f219ca0a6c1c9"
        },
        "metadata": {
            "key": "background/location",
            "platform": "android",
            "read_ts": 0,
            "time_zone": "America/Los_Angeles",
            "type": "sensor-data",
            "write_ts": 1564320200.988
        },
        "user_id": {
            "$uuid": "6a2dbafdef1e404cb61e506b8935dca4"
        },
        "data": {
            "accuracy": 5.666,
            "altitude": -6,
            "bearing": 0,
            "elapsedRealtimeNanos": 2113144654703938,
            "filter": "time",
            "fmt_time": "Jul 28, 2019 6:23:21 AM",
            "latitude": 37.3910595,
            "longitude": -122.0865127,
            "sensed_speed": 0,
            "ts": 1564320201,
            "write_ts": 1564320200.988
        }
    },
    {
        "_id": {
            "$oid": "5d3daaceb88f219ca0a6c1cb"
        },
        "metadata": {
            "key": "background/location",
            "platform": "android",
            "read_ts": 0,
            "time_zone": "America/Los_Angeles",
            "type": "sensor-data",
            "write_ts": 1564320202.027
        },
        "user_id": {
            "$uuid": "6a2dbafdef1e404cb61e506b8935dca4"
        },
        "data": {
            "accuracy": 5.63,
            "altitude": -5,
            "bearing": 0,
            "elapsedRealtimeNanos": 2113145678169666,
            "filter": "time",
            "fmt_time": "Jul 28, 2019 6:23:22 AM",
            "latitude": 37.391059,
            "longitude": -122.0865082,
            "sensed_speed": 0,
            "ts": 1564320202,
            "write_ts": 1564320202.027
        }
    },
    {
        "_id": {
            "$oid": "5d3daaceb88f219ca0a6c1cd"
        },
        "metadata": {
            "key": "background/location",
            "platform": "android",
            "read_ts": 0,
            "time_zone": "America/Los_Angeles",
            "type": "sensor-data",
            "write_ts": 1564320203.074
        },
        "user_id": {
            "$uuid": "6a2dbafdef1e404cb61e506b8935dca4"
        },
        "data": {
            "accuracy": 5.603,
            "altitude": -2,
            "bearing": 0,
            "elapsedRealtimeNanos": 2113146683700604,
            "filter": "time",
            "fmt_time": "Jul 28, 2019 6:23:23 AM",
            "latitude": 37.391058,
            "longitude": -122.0865056,
            "sensed_speed": 0,
            "ts": 1564320203,
            "write_ts": 1564320203.074
        }
    },
    {
        "_id": {
            "$oid": "5d3daaceb88f219ca0a6c1cf"
        },
        "metadata": {
            "key": "background/location",
            "platform": "android",
            "read_ts": 0,
            "time_zone": "America/Los_Angeles",
            "type": "sensor-data",
            "write_ts": 1564320204.051
        },
        "user_id": {
            "$uuid": "6a2dbafdef1e404cb61e506b8935dca4"
        },
        "data": {
            "accuracy": 5.585,
            "altitude": -5,
            "bearing": 0,
            "elapsedRealtimeNanos": 2113147683057791,
            "filter": "time",
            "fmt_time": "Jul 28, 2019 6:23:24 AM",
            "latitude": 37.3910594,
            "longitude": -122.0865053,
            "sensed_speed": 0,
            "ts": 1564320204,
            "write_ts": 1564320204.051
        }
    },
    {
        "_id": {
            "$oid": "5d3daaceb88f219ca0a6c1d1"
        },
        "metadata": {
            "key": "background/location",
            "platform": "android",
            "read_ts": 0,
            "time_zone": "America/Los_Angeles",
            "type": "sensor-data",
            "write_ts": 1564320209.333
        },
        "user_id": {
            "$uuid": "6a2dbafdef1e404cb61e506b8935dca4"
        },
        "data": {
            "accuracy": 5.585,
            "altitude": -5,
            "bearing": 0,
            "elapsedRealtimeNanos": 2113152944000000,
            "filter": "time",
            "fmt_time": "Jul 28, 2019 6:23:29 AM",
            "latitude": 37.3910594,
            "longitude": -122.0865053,
            "sensed_speed": 0,
            "ts": 1564320209.222,
            "write_ts": 1564320209.333
        }
    },
    {
        "_id": {
            "$oid": "5d3daaceb88f219ca0a6c1d3"
        },
        "metadata": {
            "key": "background/location",
            "platform": "android",
            "read_ts": 0,
            "time_zone": "America/Los_Angeles",
            "type": "sensor-data",
            "write_ts": 1564320227.919
        },
        "user_id": {
            "$uuid": "6a2dbafdef1e404cb61e506b8935dca4"
        },
        "data": {
            "accuracy": 5.585,
            "altitude": -5,
            "bearing": 0,
            "elapsedRealtimeNanos": 2113171547000000,
            "filter": "time",
            "fmt_time": "Jul 28, 2019 6:23:47 AM",
            "latitude": 37.3910594,
            "longitude": -122.0865053,
            "sensed_speed": 0,
            "ts": 1564320227.825,
            "write_ts": 1564320227.919
        }
    },
    {
        "_id": {
            "$oid": "5d3daaceb88f219ca0a6c1d5"
        },
        "metadata": {
            "key": "background/location",
            "platform": "android",
            "read_ts": 0,
            "time_zone": "America/Los_Angeles",
            "type": "sensor-data",
            "write_ts": 1564320494.994
        },
        "user_id": {
            "$uuid": "6a2dbafdef1e404cb61e506b8935dca4"
        },
        "data": {
            "accuracy": 5.585,
            "altitude": -5,
            "bearing": 0,
            "elapsedRealtimeNanos": 2113438640000000,
            "filter": "time",
            "fmt_time": "Jul 28, 2019 6:28:14 AM",
            "latitude": 37.3910594,
            "longitude": -122.0865053,
            "sensed_speed": 0,
            "ts": 1564320494.917,
            "write_ts": 1564320494.994
        }
    },
    {
        "_id": {
            "$oid": "5d3daaceb88f219ca0a6c1d7"
        },
        "metadata": {
            "key": "background/location",
            "platform": "android",
            "read_ts": 0,
            "time_zone": "America/Los_Angeles",
            "type": "sensor-data",
            "write_ts": 1564320498.14
        },
        "user_id": {
            "$uuid": "6a2dbafdef1e404cb61e506b8935dca4"
        },
        "data": {
            "accuracy": 15.473,
            "altitude": -3.4000000953674316,
            "bearing": 0,
            "elapsedRealtimeNanos": 2113441244000000,
            "filter": "time",
            "fmt_time": "Jul 28, 2019 6:28:17 AM",
            "latitude": 37.3910397,
            "longitude": -122.0864654,
            "sensed_speed": 0,
            "ts": 1564320497.521,
            "write_ts": 1564320498.14
        }
    },
    {
        "_id": {
            "$oid": "5d3daaceb88f219ca0a6c1d9"
        },
        "metadata": {
            "key": "background/location",
            "platform": "android",
            "read_ts": 0,
            "time_zone": "America/Los_Angeles",
            "type": "sensor-data",
            "write_ts": 1564320504.886
        },
        "user_id": {
            "$uuid": "6a2dbafdef1e404cb61e506b8935dca4"
        },
        "data": {
            "accuracy": 15.473,
            "altitude": -3.4000000953674316,
            "bearing": 0,
            "elapsedRealtimeNanos": 2113448548000000,
            "filter": "time",
            "fmt_time": "Jul 28, 2019 6:28:24 AM",
            "latitude": 37.3910397,
            "longitude": -122.0864654,
            "sensed_speed": 0,
            "ts": 1564320504.825,
            "write_ts": 1564320504.886
        }
    },
    {
        "_id": {
            "$oid": "5d3daaceb88f219ca0a6c1dd"
        },
        "metadata": {
            "key": "background/location",
            "platform": "android",
            "read_ts": 0,
            "time_zone": "America/Los_Angeles",
            "type": "sensor-data",
            "write_ts": 1564320765.959
        },
        "user_id": {
            "$uuid": "6a2dbafdef1e404cb61e506b8935dca4"
        },
        "data": {
            "accuracy": 15.473,
            "altitude": -3.4000000953674316,
            "bearing": 0,
            "elapsedRealtimeNanos": 2113709610000000,
            "filter": "time",
            "fmt_time": "Jul 28, 2019 6:32:45 AM",
            "latitude": 37.3910397,
            "longitude": -122.0864654,
            "sensed_speed": 0,
            "ts": 1564320765.887,
            "write_ts": 1564320765.959
        }
    },
    {
        "_id": {
            "$oid": "5d3daaceb88f219ca0a6c1df"
        },
        "metadata": {
            "key": "background/location",
            "platform": "android",
            "read_ts": 0,
            "time_zone": "America/Los_Angeles",
            "type": "sensor-data",
            "write_ts": 1564320798.938
        },
        "user_id": {
            "$uuid": "6a2dbafdef1e404cb61e506b8935dca4"
        },
        "data": {
            "accuracy": 15.473,
            "altitude": -3.4000000953674316,
            "bearing": 0,
            "elapsedRealtimeNanos": 2113742585000000,
            "filter": "time",
            "fmt_time": "Jul 28, 2019 6:33:18 AM",
            "latitude": 37.3910397,
            "longitude": -122.0864654,
            "sensed_speed": 0,
            "ts": 1564320798.863,
            "write_ts": 1564320798.938
        }
    },
    {
        "_id": {
            "$oid": "5d3daaceb88f219ca0a6c1e1"
        },
        "metadata": {
            "key": "background/location",
            "platform": "android",
            "read_ts": 0,
            "time_zone": "America/Los_Angeles",
            "type": "sensor-data",
            "write_ts": 1564322506.297
        },
        "user_id": {
            "$uuid": "6a2dbafdef1e404cb61e506b8935dca4"
        },
        "data": {
            "accuracy": 15.422,
            "altitude": -3.4000000953674316,
            "bearing": 0,
            "elapsedRealtimeNanos": 2115449933000000,
            "filter": "time",
            "fmt_time": "Jul 28, 2019 7:01:46 AM",
            "latitude": 37.3910398,
            "longitude": -122.0864653,
            "sensed_speed": 0,
            "ts": 1564322506.21,
            "write_ts": 1564322506.297
        }
    }
]