[
    {
        "_id": {
            "$oid": "639e4ad4f38e010b96a0ff34"
        },
        "user_id": {
            "$uuid": "1377b14507144a139a1edbc0dcd6fafe"
        },
        "metadata": {
            "key": "segmentation/raw_section",
            "platform": "server",
            "write_ts": 1671318228.873543,
            "time_zone": "America/Los_Angeles",
            "write_local_dt": {
                "year": 2022,
                "month": 12,
                "day": 17,
                "hour": 15,
                "minute": 3,
                "second": 48,
                "weekday": 5,
                "timezone": "America/Los_Angeles"
            },
            "write_fmt_time": "2022-12-17T15:03:48.873543-08:00"
        },
        "data": {
            "trip_id": {
                "$oid": "639e4a8ef38e010b96a0fd39"
            },
            "start_ts": 1574266346.947,
            "start_local_dt": {
                "year": 2019,
                "month": 11,
                "day": 20,
                "hour": 8,
                "minute": 12,
                "second": 26,
                "weekday": 2,
                "timezone": "America/Los_Angeles"
            },
            "start_fmt_time": "2019-11-20T08:12:26.947000-08:00",
            "end_ts": 1574267246.955,
            "end_local_dt": {
                "year": 2019,
                "month": 11,
                "day": 20,
                "hour": 8,
                "minute": 27,
                "second": 26,
                "weekday": 2,
                "timezone": "America/Los_Angeles"
            },
            "end_fmt_time": "2019-11-20T08:27:26.955000-08:00",
            "start_loc": {
                "type": "Point",
                "coordinates": [
                    -122.0823683,
                    37.3895145
                ]
            },
            "end_loc": {
                "type": "Point",
                "coordinates": [
                    -122.0751118,
                    37.3941522
                ]
            },
            "duration": 900.0079998970032,
            "source": "SmoothedHighConfidenceMotion",
            "sensed_mode": 2,
            "end_stop": {
                "$oid": "639e4ad4f38e010b96a0ff36"
            },
            "write_ts": 1671318228.873543
        }
    },
    {
        "_id": {
            "$oid": "639e4ad4f38e010b96a0ff35"
        },
        "user_id": {
            "$uuid": "1377b14507144a139a1edbc0dcd6fafe"
        },
        "metadata": {
            "key": "segmentation/raw_section",
            "platform": "server",
            "write_ts": 1671318228.880631,
            "time_zone": "America/Los_Angeles",
            "write_local_dt": {
                "year": 2022,
                "month": 12,
                "day": 17,
                "hour": 15,
                "minute": 3,
                "second": 48,
                "weekday": 5,
                "timezone": "America/Los_Angeles"
            },
            "write_fmt_time": "2022-12-17T15:03:48.880631-08:00"
        },
        "data": {
            "trip_id": {
                "$oid": "639e4a8ef38e010b96a0fd39"
            },
            "start_ts": 1574267343.082,
            "start_local_dt": {
                "year": 2019,
                "month": 11,
                "day": 20,
                "hour": 8,
                "minute": 29,
                "second": 3,
                "weekday": 2,
                "timezone": "America/Los_Angeles"
            },
            "start_fmt_time": "2019-11-20T08:29:03.082000-08:00",
            "end_ts": 1574269788,
            "end_local_dt": {
                "year": 2019,
                "month": 11,
                "day": 20,
                "hour": 9,
                "minute": 9,
                "second": 48,
                "weekday": 2,
                "timezone": "America/Los_Angeles"
            },
            "end_fmt_time": "2019-11-20T09:09:48-08:00",
            "start_loc": {
                "type": "Point",
                "coordinates": [
                    -122.0764101,
                    37.3938229
                ]
            },
            "end_loc": {
                "type": "Point",
                "coordinates": [
                    -122.3870978,
                    37.600561
                ]
            },
            "duration": 2444.917999982834,
            "source": "SmoothedHighConfidenceMotion",
            "sensed_mode": 0,
            "start_stop": {
                "$oid": "639e4ad4f38e010b96a0ff36"
            },
            "write_ts": 1671318228.880631
        }
    },
    {
        "_id": {
            "$oid": "639e4ad5f38e010b96a0ff37"
        },
        "user_id": {
            "$uuid": "1377b14507144a139a1edbc0dcd6fafe"
        },
        "metadata": {
            "key": "segmentation/raw_section",
            "platform": "server",
            "write_ts": 1671318229.099762,
            "time_zone": "America/Los_Angeles",
            "write_local_dt": {
                "year": 2022,
                "month": 12,
                "day": 17,
                "hour": 15,
                "minute": 3,
                "second": 49,
                "weekday": 5,
                "timezone": "America/Los_Angeles"
            },
            "write_fmt_time": "2022-12-17T15:03:49.099762-08:00"
        },
        "data": {
            "trip_id": {
                "$oid": "639e4a8ef38e010b96a0fd3d"
            },
            "start_ts": 1574270187.775,
            "start_local_dt": {
                "year": 2019,
                "month": 11,
                "day": 20,
                "hour": 9,
                "minute": 16,
                "second": 27,
                "weekday": 2,
                "timezone": "America/Los_Angeles"
            },
            "start_fmt_time": "2019-11-20T09:16:27.775000-08:00",
            "end_ts": 1574273667.08,
            "end_local_dt": {
                "year": 2019,
                "month": 11,
                "day": 20,
                "hour": 10,
                "minute": 14,
                "second": 27,
                "weekday": 2,
                "timezone": "America/Los_Angeles"
            },
            "end_fmt_time": "2019-11-20T10:14:27.080000-08:00",
            "start_loc": {
                "type": "Point",
                "coordinates": [
                    -122.3873696,
                    37.6021896
                ]
            },
            "end_loc": {
                "type": "Point",
                "coordinates": [
                    -122.2680905,
                    37.8701278
                ]
            },
            "duration": 3479.3049998283386,
            "source": "SmoothedHighConfidenceMotion",
            "sensed_mode": 0,
            "end_stop": {
                "$oid": "639e4ad5f38e010b96a0ff39"
            },
            "write_ts": 1671318229.099762
        }
    },
    {
        "_id": {
            "$oid": "639e4ad5f38e010b96a0ff38"
        },
        "user_id": {
            "$uuid": "1377b14507144a139a1edbc0dcd6fafe"
        },
        "metadata": {
            "key": "segmentation/raw_section",
            "platform": "server",
            "write_ts": 1671318229.106755,
            "time_zone": "America/Los_Angeles",
            "write_local_dt": {
                "year": 2022,
                "month": 12,
                "day": 17,
                "hour": 15,
                "minute": 3,
                "second": 49,
                "weekday": 5,
                "timezone": "America/Los_Angeles"
            },
            "write_fmt_time": "2022-12-17T15:03:49.106755-08:00"
        },
        "data": {
            "trip_id": {
                "$oid": "639e4a8ef38e010b96a0fd3d"
            },
            "start_ts": 1574273698.354,
            "start_local_dt": {
                "year": 2019,
                "month": 11,
                "day": 20,
                "hour": 10,
                "minute": 14,
                "second": 58,
                "weekday": 2,
                "timezone": "America/Los_Angeles"
            },
            "start_fmt_time": "2019-11-20T10:14:58.354000-08:00",
            "end_ts": 1574273953.196,
            "end_local_dt": {
                "year": 2019,
                "month": 11,
                "day": 20,
                "hour": 10,
                "minute": 19,
                "second": 13,
                "weekday": 2,
                "timezone": "America/Los_Angeles"
            },
            "end_fmt_time": "2019-11-20T10:19:13.196000-08:00",
            "start_loc": {
                "type": "Point",
                "coordinates": [
                    -122.2680278,
                    37.8701569
                ]
            },
            "end_loc": {
                "type": "Point",
                "coordinates": [
                    -122.2677232,
                    37.8711119
                ]
            },
            "duration": 254.8420000076294,
            "source": "SmoothedHighConfidenceMotion",
            "sensed_mode": 2,
            "start_stop": {
                "$oid": "639e4ad5f38e010b96a0ff39"
            },
            "write_ts": 1671318229.106755
        }
    },
    {
        "_id": {
            "$oid": "639e4ad5f38e010b96a0ff3a"
        },
        "user_id": {
            "$uuid": "1377b14507144a139a1edbc0dcd6fafe"
        },
        "metadata": {
            "key": "segmentation/raw_section",
            "platform": "server",
            "write_ts": 1671318229.193501,
            "time_zone": "America/Los_Angeles",
            "write_local_dt": {
                "year": 2022,
                "month": 12,
                "day": 17,
                "hour": 15,
                "minute": 3,
                "second": 49,
                "weekday": 5,
                "timezone": "America/Los_Angeles"
            },
            "write_fmt_time": "2022-12-17T15:03:49.193501-08:00"
        },
        "data": {
            "trip_id": {
                "$oid": "639e4a8ff38e010b96a0fd3f"
            },
            "start_ts": 1574274400.697,
            "start_local_dt": {
                "year": 2019,
                "month": 11,
                "day": 20,
                "hour": 10,
                "minute": 26,
                "second": 40,
                "weekday": 2,
                "timezone": "America/Los_Angeles"
            },
            "start_fmt_time": "2019-11-20T10:26:40.697000-08:00",
            "end_ts": 1574274719.682,
            "end_local_dt": {
                "year": 2019,
                "month": 11,
                "day": 20,
                "hour": 10,
                "minute": 31,
                "second": 59,
                "weekday": 2,
                "timezone": "America/Los_Angeles"
            },
            "end_fmt_time": "2019-11-20T10:31:59.682000-08:00",
            "start_loc": {
                "type": "Point",
                "coordinates": [
                    -122.2671013,
                    37.872213
                ]
            },
            "end_loc": {
                "type": "Point",
                "coordinates": [
                    -122.2585564,
                    37.8755623
                ]
            },
            "duration": 318.9849998950958,
            "source": "SmoothedHighConfidenceMotion",
            "sensed_mode": 0,
            "write_ts": 1671318229.193501
        }
    },
    {
        "_id": {
            "$oid": "639e4ad5f38e010b96a0ff3b"
        },
        "user_id": {
            "$uuid": "1377b14507144a139a1edbc0dcd6fafe"
        },
        "metadata": {
            "key": "segmentation/raw_section",
            "platform": "server",
            "write_ts": 1671318229.440025,
            "time_zone": "America/Los_Angeles",
            "write_local_dt": {
                "year": 2022,
                "month": 12,
                "day": 17,
                "hour": 15,
                "minute": 3,
                "second": 49,
                "weekday": 5,
                "timezone": "America/Los_Angeles"
            },
            "write_fmt_time": "2022-12-17T15:03:49.440025-08:00"
        },
        "data": {
            "trip_id": {
                "$oid": "639e4a8ff38e010b96a0fd45"
            },
            "start_ts": 1574286390.818,
            "start_local_dt": {
                "year": 2019,
                "month": 11,
                "day": 20,
                "hour": 13,
                "minute": 46,
                "second": 30,
                "weekday": 2,
                "timezone": "America/Los_Angeles"
            },
            "start_fmt_time": "2019-11-20T13:46:30.818000-08:00",
            "end_ts": 1574287181.806,
            "end_local_dt": {
                "year": 2019,
                "month": 11,
                "day": 20,
                "hour": 13,
                "minute": 59,
                "second": 41,
                "weekday": 2,
                "timezone": "America/Los_Angeles"
            },
            "end_fmt_time": "2019-11-20T13:59:41.806000-08:00",
            "start_loc": {
                "type": "Point",
                "coordinates": [
                    -122.258383,
                    37.8755534
                ]
            },
            "end_loc": {
                "type": "Point",
                "coordinates": [
                    -122.2577042,
                    37.8695222
                ]
            },
            "duration": 790.9879999160767,
            "source": "SmoothedHighConfidenceMotion",
            "sensed_mode": 2,
            "write_ts": 1671318229.440025
        }
    },
    {
        "_id": {
            "$oid": "639e4ad5f38e010b96a0ff3c"
        },
        "user_id": {
            "$uuid": "1377b14507144a139a1edbc0dcd6fafe"
        },
        "metadata": {
            "key": "segmentation/raw_section",
            "platform": "server",
            "write_ts": 1671318229.731061,
            "time_zone": "America/Los_Angeles",
            "write_local_dt": {
                "year": 2022,
                "month": 12,
                "day": 17,
                "hour": 15,
                "minute": 3,
                "second": 49,
                "weekday": 5,
                "timezone": "America/Los_Angeles"
            },
            "write_fmt_time": "2022-12-17T15:03:49.731061-08:00"
        },
        "data": {
            "trip_id": {
                "$oid": "639e4a8ff38e010b96a0fd4b"
            },
            "start_ts": 1574295431.861,
            "start_local_dt": {
                "year": 2019,
                "month": 11,
                "day": 20,
                "hour": 16,
                "minute": 17,
                "second": 11,
                "weekday": 2,
                "timezone": "America/Los_Angeles"
            },
            "start_fmt_time": "2019-11-20T16:17:11.861000-08:00",
            "end_ts": 1574295823.816,
            "end_local_dt": {
                "year": 2019,
                "month": 11,
                "day": 20,
                "hour": 16,
                "minute": 23,
                "second": 43,
                "weekday": 2,
                "timezone": "America/Los_Angeles"
            },
            "end_fmt_time": "2019-11-20T16:23:43.816000-08:00",
            "start_loc": {
                "type": "Point",
                "coordinates": [
                    -122.2576726,
                    37.8694983
                ]
            },
            "end_loc": {
                "type": "Point",
                "coordinates": [
                    -122.2545846,
                    37.8690805
                ]
            },
            "duration": 391.95499992370605,
            "source": "SmoothedHighConfidenceMotion",
            "sensed_mode": 2,
            "end_stop": {
                "$oid": "639e4ad5f38e010b96a0ff3e"
            },
            "write_ts": 1671318229.731061
        }
    },
    {
        "_id": {
            "$oid": "639e4ad5f38e010b96a0ff3d"
        },
        "user_id": {
            "$uuid": "1377b14507144a139a1edbc0dcd6fafe"
        },
        "metadata": {
            "key": "segmentation/raw_section",
            "platform": "server",
            "write_ts": 1671318229.738256,
            "time_zone": "America/Los_Angeles",
            "write_local_dt": {
                "year": 2022,
                "month": 12,
                "day": 17,
                "hour": 15,
                "minute": 3,
                "second": 49,
                "weekday": 5,
                "timezone": "America/Los_Angeles"
            },
            "write_fmt_time": "2022-12-17T15:03:49.738256-08:00"
        },
        "data": {
            "trip_id": {
                "$oid": "639e4a8ff38e010b96a0fd4b"
            },
            "start_ts": 1574295855.76,
            "start_local_dt": {
                "year": 2019,
                "month": 11,
                "day": 20,
                "hour": 16,
                "minute": 24,
                "second": 15,
                "weekday": 2,
                "timezone": "America/Los_Angeles"
            },
            "start_fmt_time": "2019-11-20T16:24:15.760000-08:00",
            "end_ts": 1574297051.819,
            "end_local_dt": {
                "year": 2019,
                "month": 11,
                "day": 20,
                "hour": 16,
                "minute": 44,
                "second": 11,
                "weekday": 2,
                "timezone": "America/Los_Angeles"
            },
            "end_fmt_time": "2019-11-20T16:44:11.819000-08:00",
            "start_loc": {
                "type": "Point",
                "coordinates": [
                    -122.2545625,
                    37.8689776
                ]
            },
            "end_loc": {
                "type": "Point",
                "coordinates": [
                    -122.2784407,
                    37.8313917
                ]
            },
            "duration": 1196.0590000152588,
            "source": "SmoothedHighConfidenceMotion",
            "sensed_mode": 1,
            "start_stop": {
                "$oid": "639e4ad5f38e010b96a0ff3e"
            },
            "end_stop": {
                "$oid": "639e4ad5f38e010b96a0ff40"
            },
            "write_ts": 1671318229.738256
        }
    },
    {
        "_id": {
            "$oid": "639e4ad5f38e010b96a0ff3f"
        },
        "user_id": {
            "$uuid": "1377b14507144a139a1edbc0dcd6fafe"
        },
        "metadata": {
            "key": "segmentation/raw_section",
            "platform": "server",
            "write_ts": 1671318229.7498372,
            "time_zone": "America/Los_Angeles",
            "write_local_dt": {
                "year": 2022,
                "month": 12,
                "day": 17,
                "hour": 15,
                "minute": 3,
                "second": 49,
                "weekday": 5,
                "timezone": "America/Los_Angeles"
            },
            "write_fmt_time": "2022-12-17T15:03:49.749837-08:00"
        },
        "data": {
            "trip_id": {
                "$oid": "639e4a8ff38e010b96a0fd4b"
            },
            "start_ts": 1574297083.788,
            "start_local_dt": {
                "year": 2019,
                "month": 11,
                "day": 20,
                "hour": 16,
                "minute": 44,
                "second": 43,
                "weekday": 2,
                "timezone": "America/Los_Angeles"
            },
            "start_fmt_time": "2019-11-20T16:44:43.788000-08:00",
            "end_ts": 1574297115.798,
            "end_local_dt": {
                "year": 2019,
                "month": 11,
                "day": 20,
                "hour": 16,
                "minute": 45,
                "second": 15,
                "weekday": 2,
                "timezone": "America/Los_Angeles"
            },
            "end_fmt_time": "2019-11-20T16:45:15.798000-08:00",
            "start_loc": {
                "type": "Point",
                "coordinates": [
                    -122.2786686,
                    37.8312683
                ]
            },
            "end_loc": {
                "type": "Point",
                "coordinates": [
                    -122.2793396,
                    37.8311076
                ]
            },
            "duration": 32.00999999046326,
            "source": "SmoothedHighConfidenceMotion",
            "sensed_mode": 2,
            "start_stop": {
                "$oid": "639e4ad5f38e010b96a0ff40"
            },
            "end_stop": {
                "$oid": "639e4ad5f38e010b96a0ff42"
            },
            "write_ts": 1671318229.7498372
        }
    },
    {
        "_id": {
            "$oid": "639e4ad5f38e010b96a0ff41"
        },
        "user_id": {
            "$uuid": "1377b14507144a139a1edbc0dcd6fafe"
        },
        "metadata": {
            "key": "segmentation/raw_section",
            "platform": "server",
            "write_ts": 1671318229.760938,
            "time_zone": "America/Los_Angeles",
            "write_local_dt": {
                "year": 2022,
                "month": 12,
                "day": 17,
                "hour": 15,
                "minute": 3,
                "second": 49,
                "weekday": 5,
                "timezone": "America/Los_Angeles"
            },
            "write_fmt_time": "2022-12-17T15:03:49.760938-08:00"
        },
        "data": {
            "trip_id": {
                "$oid": "639e4a8ff38e010b96a0fd4b"
            },
            "start_ts": 1574297146.85,
            "start_local_dt": {
                "year": 2019,
                "month": 11,
                "day": 20,
                "hour": 16,
                "minute": 45,
                "second": 46,
                "weekday": 2,
                "timezone": "America/Los_Angeles"
            },
            "start_fmt_time": "2019-11-20T16:45:46.850000-08:00",
            "end_ts": 1574297250,
            "end_local_dt": {
                "year": 2019,
                "month": 11,
                "day": 20,
                "hour": 16,
                "minute": 47,
                "second": 30,
                "weekday": 2,
                "timezone": "America/Los_Angeles"
            },
            "end_fmt_time": "2019-11-20T16:47:30-08:00",
            "start_loc": {
                "type": "Point",
                "coordinates": [
                    -122.2791378,
                    37.8312545
                ]
            },
            "end_loc": {
                "type": "Point",
                "coordinates": [
                    -122.2794709,
                    37.831163
                ]
            },
            "duration": 103.15000009536743,
            "source": "SmoothedHighConfidenceMotion",
            "sensed_mode": 0,
            "start_stop": {
                "$oid": "639e4ad5f38e010b96a0ff42"
            },
            "write_ts": 1671318229.760938
        }
    },
    {
        "_id": {
            "$oid": "639e4ad6f38e010b96a0ff43"
        },
        "user_id": {
            "$uuid": "1377b14507144a139a1edbc0dcd6fafe"
        },
        "metadata": {
            "key": "segmentation/raw_section",
            "platform": "server",
            "write_ts": 1671318230.3133922,
            "time_zone": "America/Los_Angeles",
            "write_local_dt": {
                "year": 2022,
                "month": 12,
                "day": 17,
                "hour": 15,
                "minute": 3,
                "second": 50,
                "weekday": 5,
                "timezone": "America/Los_Angeles"
            },
            "write_fmt_time": "2022-12-17T15:03:50.313392-08:00"
        },
        "data": {
            "trip_id": {
                "$oid": "639e4a8ff38e010b96a0fd4f"
            },
            "start_ts": 1574299062.048,
            "start_local_dt": {
                "year": 2019,
                "month": 11,
                "day": 20,
                "hour": 17,
                "minute": 17,
                "second": 42,
                "weekday": 2,
                "timezone": "America/Los_Angeles"
            },
            "start_fmt_time": "2019-11-20T17:17:42.048000-08:00",
            "end_ts": 1574301041.894,
            "end_local_dt": {
                "year": 2019,
                "month": 11,
                "day": 20,
                "hour": 17,
                "minute": 50,
                "second": 41,
                "weekday": 2,
                "timezone": "America/Los_Angeles"
            },
            "end_fmt_time": "2019-11-20T17:50:41.894000-08:00",
            "start_loc": {
                "type": "Point",
                "coordinates": [
                    -122.2843622,
                    37.8301599
                ]
            },
            "end_loc": {
                "type": "Point",
                "coordinates": [
                    -122.3953651,
                    37.7909298
                ]
            },
            "duration": 1979.845999956131,
            "source": "SmoothedHighConfidenceMotion",
            "sensed_mode": 0,
            "end_stop": {
                "$oid": "639e4ad6f38e010b96a0ff45"
            },
            "write_ts": 1671318230.3133922
        }
    },
    {
        "_id": {
            "$oid": "639e4ad6f38e010b96a0ff44"
        },
        "user_id": {
            "$uuid": "1377b14507144a139a1edbc0dcd6fafe"
        },
        "metadata": {
            "key": "segmentation/raw_section",
            "platform": "server",
            "write_ts": 1671318230.3202891,
            "time_zone": "America/Los_Angeles",
            "write_local_dt": {
                "year": 2022,
                "month": 12,
                "day": 17,
                "hour": 15,
                "minute": 3,
                "second": 50,
                "weekday": 5,
                "timezone": "America/Los_Angeles"
            },
            "write_fmt_time": "2022-12-17T15:03:50.320289-08:00"
        },
        "data": {
            "trip_id": {
                "$oid": "639e4a8ff38e010b96a0fd4f"
            },
            "start_ts": 1574301073.823,
            "start_local_dt": {
                "year": 2019,
                "month": 11,
                "day": 20,
                "hour": 17,
                "minute": 51,
                "second": 13,
                "weekday": 2,
                "timezone": "America/Los_Angeles"
            },
            "start_fmt_time": "2019-11-20T17:51:13.823000-08:00",
            "end_ts": 1574301466.822,
            "end_local_dt": {
                "year": 2019,
                "month": 11,
                "day": 20,
                "hour": 17,
                "minute": 57,
                "second": 46,
                "weekday": 2,
                "timezone": "America/Los_Angeles"
            },
            "end_fmt_time": "2019-11-20T17:57:46.822000-08:00",
            "start_loc": {
                "type": "Point",
                "coordinates": [
                    -122.395409,
                    37.7909887
                ]
            },
            "end_loc": {
                "type": "Point",
                "coordinates": [
                    -122.3966416,
                    37.7930804
                ]
            },
            "duration": 392.99900007247925,
            "source": "SmoothedHighConfidenceMotion",
            "sensed_mode": 2,
            "start_stop": {
                "$oid": "639e4ad6f38e010b96a0ff45"
            },
            "end_stop": {
                "$oid": "639e4ad6f38e010b96a0ff47"
            },
            "write_ts": 1671318230.3202891
        }
    },
    {
        "_id": {
            "$oid": "639e4ad6f38e010b96a0ff46"
        },
        "user_id": {
            "$uuid": "1377b14507144a139a1edbc0dcd6fafe"
        },
        "metadata": {
            "key": "segmentation/raw_section",
            "platform": "server",
            "write_ts": 1671318230.33148,
            "time_zone": "America/Los_Angeles",
            "write_local_dt": {
                "year": 2022,
                "month": 12,
                "day": 17,
                "hour": 15,
                "minute": 3,
                "second": 50,
                "weekday": 5,
                "timezone": "America/Los_Angeles"
            },
            "write_fmt_time": "2022-12-17T15:03:50.331480-08:00"
        },
        "data": {
            "trip_id": {
                "$oid": "639e4a8ff38e010b96a0fd4f"
            },
            "start_ts": 1574301499.939,
            "start_local_dt": {
                "year": 2019,
                "month": 11,
                "day": 20,
                "hour": 17,
                "minute": 58,
                "second": 19,
                "weekday": 2,
                "timezone": "America/Los_Angeles"
            },
            "start_fmt_time": "2019-11-20T17:58:19.939000-08:00",
            "end_ts": 1574302362.631,
            "end_local_dt": {
                "year": 2019,
                "month": 11,
                "day": 20,
                "hour": 18,
                "minute": 12,
                "second": 42,
                "weekday": 2,
                "timezone": "America/Los_Angeles"
            },
            "end_fmt_time": "2019-11-20T18:12:42.631000-08:00",
            "start_loc": {
                "type": "Point",
                "coordinates": [
                    -122.3966854,
                    37.7930752
                ]
            },
            "end_loc": {
                "type": "Point",
                "coordinates": [
                    -122.3940269,
                    37.776443
                ]
            },
            "duration": 862.6920001506805,
            "source": "SmoothedHighConfidenceMotion",
            "sensed_mode": 0,
            "start_stop": {
                "$oid": "639e4ad6f38e010b96a0ff47"
            },
            "end_stop": {
                "$oid": "639e4ad6f38e010b96a0ff49"
            },
            "write_ts": 1671318230.33148
        }
    },
    {
        "_id": {
            "$oid": "639e4ad6f38e010b96a0ff48"
        },
        "user_id": {
            "$uuid": "1377b14507144a139a1edbc0dcd6fafe"
        },
        "metadata": {
            "key": "segmentation/raw_section",
            "platform": "server",
            "write_ts": 1671318230.342371,
            "time_zone": "America/Los_Angeles",
            "write_local_dt": {
                "year": 2022,
                "month": 12,
                "day": 17,
                "hour": 15,
                "minute": 3,
                "second": 50,
                "weekday": 5,
                "timezone": "America/Los_Angeles"
            },
            "write_fmt_time": "2022-12-17T15:03:50.342371-08:00"
        },
        "data": {
            "trip_id": {
                "$oid": "639e4a8ff38e010b96a0fd4f"
            },
            "start_ts": 1574302397.432,
            "start_local_dt": {
                "year": 2019,
                "month": 11,
                "day": 20,
                "hour": 18,
                "minute": 13,
                "second": 17,
                "weekday": 2,
                "timezone": "America/Los_Angeles"
            },
            "start_fmt_time": "2019-11-20T18:13:17.432000-08:00",
            "end_ts": 1574302453,
            "end_local_dt": {
                "year": 2019,
                "month": 11,
                "day": 20,
                "hour": 18,
                "minute": 14,
                "second": 13,
                "weekday": 2,
                "timezone": "America/Los_Angeles"
            },
            "end_fmt_time": "2019-11-20T18:14:13-08:00",
            "start_loc": {
                "type": "Point",
                "coordinates": [
                    -122.3948327,
                    37.7759099
                ]
            },
            "end_loc": {
                "type": "Point",
                "coordinates": [
                    -122.3953262,
                    37.7759204
                ]
            },
            "duration": 55.568000078201294,
            "source": "SmoothedHighConfidenceMotion",
            "sensed_mode": 2,
            "start_stop": {
                "$oid": "639e4ad6f38e010b96a0ff49"
            },
            "end_stop": {
                "$oid": "639e4ad6f38e010b96a0ff4b"
            },
            "write_ts": 1671318230.342371
        }
    },
    {
        "_id": {
            "$oid": "639e4ad6f38e010b96a0ff4a"
        },
        "user_id": {
            "$uuid": "1377b14507144a139a1edbc0dcd6fafe"
        },
        "metadata": {
            "key": "segmentation/raw_section",
            "platform": "server",
            "write_ts": 1671318230.3534012,
            "time_zone": "America/Los_Angeles",
            "write_local_dt": {
                "year": 2022,
                "month": 12,
                "day": 17,
                "hour": 15,
                "minute": 3,
                "second": 50,
                "weekday": 5,
                "timezone": "America/Los_Angeles"
            },
            "write_fmt_time": "2022-12-17T15:03:50.353401-08:00"
        },
        "data": {
            "trip_id": {
                "$oid": "639e4a8ff38e010b96a0fd4f"
            },
            "start_ts": 1574302459,
            "start_local_dt": {
                "year": 2019,
                "month": 11,
                "day": 20,
                "hour": 18,
                "minute": 14,
                "second": 19,
                "weekday": 2,
                "timezone": "America/Los_Angeles"
            },
            "start_fmt_time": "2019-11-20T18:14:19-08:00",
            "end_ts": 1574305485.847,
            "end_local_dt": {
                "year": 2019,
                "month": 11,
                "day": 20,
                "hour": 19,
                "minute": 4,
                "second": 45,
                "weekday": 2,
                "timezone": "America/Los_Angeles"
            },
            "end_fmt_time": "2019-11-20T19:04:45.847000-08:00",
            "start_loc": {
                "type": "Point",
                "coordinates": [
                    -122.3953357,
                    37.7759061
                ]
            },
            "end_loc": {
                "type": "Point",
                "coordinates": [
                    -122.077131,
                    37.3941507
                ]
            },
            "duration": 3026.8469998836517,
            "source": "SmoothedHighConfidenceMotion",
            "sensed_mode": 0,
            "start_stop": {
                "$oid": "639e4ad6f38e010b96a0ff4b"
            },
            "end_stop": {
                "$oid": "639e4ad6f38e010b96a0ff4d"
            },
            "write_ts": 1671318230.3534012
        }
    },
    {
        "_id": {
            "$oid": "639e4ad6f38e010b96a0ff4c"
        },
        "user_id": {
            "$uuid": "1377b14507144a139a1edbc0dcd6fafe"
        },
        "metadata": {
            "key": "segmentation/raw_section",
            "platform": "server",
            "write_ts": 1671318230.364513,
            "time_zone": "America/Los_Angeles",
            "write_local_dt": {
                "year": 2022,
                "month": 12,
                "day": 17,
                "hour": 15,
                "minute": 3,
                "second": 50,
                "weekday": 5,
                "timezone": "America/Los_Angeles"
            },
            "write_fmt_time": "2022-12-17T15:03:50.364513-08:00"
        },
        "data": {
            "trip_id": {
                "$oid": "639e4a8ff38e010b96a0fd4f"
            },
            "start_ts": 1574305517.765,
            "start_local_dt": {
                "year": 2019,
                "month": 11,
                "day": 20,
                "hour": 19,
                "minute": 5,
                "second": 17,
                "weekday": 2,
                "timezone": "America/Los_Angeles"
            },
            "start_fmt_time": "2019-11-20T19:05:17.765000-08:00",
            "end_ts": 1574306545.813,
            "end_local_dt": {
                "year": 2019,
                "month": 11,
                "day": 20,
                "hour": 19,
                "minute": 22,
                "second": 25,
                "weekday": 2,
                "timezone": "America/Los_Angeles"
            },
            "end_fmt_time": "2019-11-20T19:22:25.813000-08:00",
            "start_loc": {
                "type": "Point",
                "coordinates": [
                    -122.0767106,
                    37.3939014
                ]
            },
            "end_loc": {
                "type": "Point",
                "coordinates": [
                    -122.0832741,
                    37.3902669
                ]
            },
            "duration": 1028.0479998588562,
            "source": "SmoothedHighConfidenceMotion",
            "sensed_mode": 2,
            "start_stop": {
                "$oid": "639e4ad6f38e010b96a0ff4d"
            },
            "write_ts": 1671318230.364513
        }
    }
]